{"name":"Bedlam Reveler","mana_cost":"{6}{R}{R}","cmc":8.0,"type_line":"Creature - Devil Horror","colors":["R"],"power":"3","toughness":"4","keywords":{"Mode$":["ChangesZone"],"ValidCard$":["Card.Self"],"Origin$":["Any"],"TriggerDescription$":["When CARDNAME enters the battlefield"," discard your hand"," then draw three cards."],"Destination$":["Battlefield"],"Execute$":["TrigDiscard"]},"image_uris":{"normal":"https://img.scryfall.com/cards/normal/front/0/2/0232f188-44f2-4aee-963c-6f6edc4a21ac.jpg?1576384515"}}
{"name":"Convolute","mana_cost":"{2}{U}","cmc":3.0,"type_line":"Instant","colors":["U"],"keywords":{"SpellDescription$":["Counter target spell unless its controller pays {4}."],"SP$":["Counter"],"TargetType$":["Spell"],"ValidTgts$":["Card"],"TgtPrompt$":["Select target spell"]},"image_uris":{"normal":"https://img.scryfall.com/cards/normal/front/b/8/b8a68347-c0ef-46ff-9705-6d82d004d32c.jpg?1563898570"}}
{"name":"Dance with Devils","mana_cost":"{3}{R}","cmc":4.0,"type_line":"Instant","colors":["R"],"keywords":{"SpellDescription$":["Create two 1/1 red Devil creature tokens. They have \"When this creature dies"," it deals 1 damage to any target.\""],"TokenScript$":["r_1_1_devil_burn"],"LegacyImage$":["r 1 1 devil burn soi"],"SP$":["Token"],"TokenOwner$":["You"],"TokenAmount$":["2"]},"image_uris":{"normal":"https://img.scryfall.com/cards/normal/front/f/1/f1112ebe-2a42-48b9-b0e5-f708305d088a.jpg?1576384694"}}
{"name":"Drag Under","mana_cost":"{2}{U}","cmc":3.0,"type_line":"Sorcery","colors":["U"],"keywords":{"Origin$":["Battlefield"],"SubAbility$":["DBDraw"],"SpellDescription$":["Return target creature to its owners hand. Draw a card."],"SP$":["ChangeZone"],"ValidTgts$":["Creature"],"TgtPrompt$":["Select target creature"],"Destination$":["Hand"]},"image_uris":{"normal":"https://img.scryfall.com/cards/normal/front/7/5/75eacac3-cba4-4c30-b1df-19fcc5f96076.jpg?1562199038"}}
{"name":"Galvanic Bombardment","mana_cost":"{R}","cmc":1.0,"type_line":"Instant","colors":["R"],"keywords":{"NumDmg$":["X"],"SpellDescription$":["CARDNAME deals X damage to target creature"," where X is 2 plus the number of cards named Galvanic Bombardment in your graveyard."],"SP$":["DealDamage"],"ValidTgts$":["Creature"],"TgtPrompt$":["Select target creature"],"References$":["X"]},"image_uris":{"normal":"https://img.scryfall.com/cards/normal/front/d/c/dc6a4367-bbee-43b8-b5dd-28498f8e2ede.jpg?1576384589"}}
{"name":"Galvanic Bombardment","mana_cost":"{R}","cmc":1.0,"type_line":"Instant","colors":["R"],"keywords":{"NumDmg$":["X"],"SpellDescription$":["CARDNAME deals X damage to target creature"," where X is 2 plus the number of cards named Galvanic Bombardment in your graveyard."],"SP$":["DealDamage"],"ValidTgts$":["Creature"],"TgtPrompt$":["Select target creature"],"References$":["X"]},"image_uris":{"normal":"https://img.scryfall.com/cards/normal/front/d/c/dc6a4367-bbee-43b8-b5dd-28498f8e2ede.jpg?1576384589"}}
{"name":"Galvanic Bombardment","mana_cost":"{R}","cmc":1.0,"type_line":"Instant","colors":["R"],"keywords":{"NumDmg$":["X"],"SpellDescription$":["CARDNAME deals X damage to target creature"," where X is 2 plus the number of cards named Galvanic Bombardment in your graveyard."],"SP$":["DealDamage"],"ValidTgts$":["Creature"],"TgtPrompt$":["Select target creature"],"References$":["X"]},"image_uris":{"normal":"https://img.scryfall.com/cards/normal/front/d/c/dc6a4367-bbee-43b8-b5dd-28498f8e2ede.jpg?1576384589"}}
{"name":"Geistblast","mana_cost":"{2}{R}","cmc":3.0,"type_line":"Instant","colors":["R"],"keywords":{"NumDmg$":["2"],"ActivationZone$":["Graveyard"],"SpellDescription$":["Copy target instant or sorcery spell you control. You may choose new targets for the copy."],"AB$":["CopySpellAbility"],"SP$":["DealDamage"],"TargetType$":["Spell"],"ValidTgts$":["Instant.YouCtrl","Sorcery.YouCtrl"],"TgtPrompt$":["Select any target"]},"image_uris":{"normal":"https://img.scryfall.com/cards/normal/front/1/9/19b1dfd9-b717-4c23-b8e5-a6ec835b278a.jpg?1576384765"}}
{"name":"Geistblast","mana_cost":"{2}{R}","cmc":3.0,"type_line":"Instant","colors":["R"],"keywords":{"NumDmg$":["2"],"ActivationZone$":["Graveyard"],"SpellDescription$":["Copy target instant or sorcery spell you control. You may choose new targets for the copy."],"AB$":["CopySpellAbility"],"SP$":["DealDamage"],"TargetType$":["Spell"],"ValidTgts$":["Instant.YouCtrl","Sorcery.YouCtrl"],"TgtPrompt$":["Select any target"]},"image_uris":{"normal":"https://img.scryfall.com/cards/normal/front/1/9/19b1dfd9-b717-4c23-b8e5-a6ec835b278a.jpg?1576384765"}}
{"name":"Incendiary Flow","mana_cost":"{1}{R}","cmc":2.0,"type_line":"Sorcery","colors":["R"],"keywords":{"NumDmg$":["3"],"SubAbility$":["DBCleanup"],"SpellDescription$":["CARDNAME deals 3 damage to any target. If a creature dealt damage this way would die this turn"," exile it instead."],"SP$":["DealDamage"],"ReplaceDyingDefined$":["Remembered"],"ValidTgts$":["Creature","Player","Planeswalker"],"TgtPrompt$":["Select any target"],"RememberDamaged$":["True"]},"image_uris":{"normal":"https://img.scryfall.com/cards/normal/front/c/f/cf464f61-8a7f-493b-a80f-2f2b0ebd8bf6.jpg?1576384613"}}
{"name":"Ingenious Skaab","mana_cost":"{2}{U}","cmc":3.0,"type_line":"Creature - Zombie Horror","colors":["U"],"power":"2","toughness":"3","keywords":{"AB$":["Pump"],"SpellDescription$":["CARDNAME gets +1/-1 until end of turn."],"NumAtt$":["+1"],"NumDef$":["-1"]},"image_uris":{"normal":"https://img.scryfall.com/cards/normal/front/1/9/19d6ed0b-40ba-407d-94de-05a705e79b95.jpg?1576384161"}}
{"name":"Ingenious Skaab","mana_cost":"{2}{U}","cmc":3.0,"type_line":"Creature - Zombie Horror","colors":["U"],"power":"2","toughness":"3","keywords":{"AB$":["Pump"],"SpellDescription$":["CARDNAME gets +1/-1 until end of turn."],"NumAtt$":["+1"],"NumDef$":["-1"]},"image_uris":{"normal":"https://img.scryfall.com/cards/normal/front/1/9/19d6ed0b-40ba-407d-94de-05a705e79b95.jpg?1576384161"}}
{"name":"Island","mana_cost":"","cmc":0.0,"type_line":"Basic Land - Island","colors":[],"keywords":{},"image_uris":{"normal":"https://img.scryfall.com/cards/normal/front/9/2/92daaa39-cd2f-4c03-8f41-92d99d0a3366.jpg?1581481496"}}
{"name":"Island","mana_cost":"","cmc":0.0,"type_line":"Basic Land - Island","colors":[],"keywords":{},"image_uris":{"normal":"https://img.scryfall.com/cards/normal/front/9/2/92daaa39-cd2f-4c03-8f41-92d99d0a3366.jpg?1581481496"}}
{"name":"Island","mana_cost":"","cmc":0.0,"type_line":"Basic Land - Island","colors":[],"keywords":{},"image_uris":{"normal":"https://img.scryfall.com/cards/normal/front/9/2/92daaa39-cd2f-4c03-8f41-92d99d0a3366.jpg?1581481496"}}
{"name":"Island","mana_cost":"","cmc":0.0,"type_line":"Basic Land - Island","colors":[],"keywords":{},"image_uris":{"normal":"https://img.scryfall.com/cards/normal/front/9/2/92daaa39-cd2f-4c03-8f41-92d99d0a3366.jpg?1581481496"}}
{"name":"Island","mana_cost":"","cmc":0.0,"type_line":"Basic Land - Island","colors":[],"keywords":{},"image_uris":{"normal":"https://img.scryfall.com/cards/normal/front/9/2/92daaa39-cd2f-4c03-8f41-92d99d0a3366.jpg?1581481496"}}
{"name":"Island","mana_cost":"","cmc":0.0,"type_line":"Basic Land - Island","colors":[],"keywords":{},"image_uris":{"normal":"https://img.scryfall.com/cards/normal/front/9/2/92daaa39-cd2f-4c03-8f41-92d99d0a3366.jpg?1581481496"}}
{"name":"Island","mana_cost":"","cmc":0.0,"type_line":"Basic Land - Island","colors":[],"keywords":{},"image_uris":{"normal":"https://img.scryfall.com/cards/normal/front/9/2/92daaa39-cd2f-4c03-8f41-92d99d0a3366.jpg?1581481496"}}
{"name":"Island","mana_cost":"","cmc":0.0,"type_line":"Basic Land - Island","colors":[],"keywords":{},"image_uris":{"normal":"https://img.scryfall.com/cards/normal/front/9/2/92daaa39-cd2f-4c03-8f41-92d99d0a3366.jpg?1581481496"}}
{"name":"Island","mana_cost":"","cmc":0.0,"type_line":"Basic Land - Island","colors":[],"keywords":{},"image_uris":{"normal":"https://img.scryfall.com/cards/normal/front/9/2/92daaa39-cd2f-4c03-8f41-92d99d0a3366.jpg?1581481496"}}
{"name":"Island","mana_cost":"","cmc":0.0,"type_line":"Basic Land - Island","colors":[],"keywords":{},"image_uris":{"normal":"https://img.scryfall.com/cards/normal/front/9/2/92daaa39-cd2f-4c03-8f41-92d99d0a3366.jpg?1581481496"}}
{"name":"Island","mana_cost":"","cmc":0.0,"type_line":"Basic Land - Island","colors":[],"keywords":{},"image_uris":{"normal":"https://img.scryfall.com/cards/normal/front/9/2/92daaa39-cd2f-4c03-8f41-92d99d0a3366.jpg?1581481496"}}
{"name":"Island","mana_cost":"","cmc":0.0,"type_line":"Basic Land - Island","colors":[],"keywords":{},"image_uris":{"normal":"https://img.scryfall.com/cards/normal/front/9/2/92daaa39-cd2f-4c03-8f41-92d99d0a3366.jpg?1581481496"}}
{"name":"Island","mana_cost":"","cmc":0.0,"type_line":"Basic Land - Island","colors":[],"keywords":{},"image_uris":{"normal":"https://img.scryfall.com/cards/normal/front/9/2/92daaa39-cd2f-4c03-8f41-92d99d0a3366.jpg?1581481496"}}
{"name":"Make Mischief","mana_cost":"{2}{R}","cmc":3.0,"type_line":"Sorcery","colors":["R"],"keywords":{"NumDmg$":["1"],"SubAbility$":["DBToken"],"SpellDescription$":["CARDNAME deals 1 damage to any target. Create a 1/1 red Devil creature token. It has \"When this creature dies"," it deals 1 damage to any target.\""],"SP$":["DealDamage"],"ValidTgts$":["Creature","Player","Planeswalker"],"TgtPrompt$":["Select any target"]},"image_uris":{"normal":"https://img.scryfall.com/cards/normal/front/a/2/a2049072-5901-4edd-8305-ce55f256bca5.jpg?1576384624"}}
{"name":"Make Mischief","mana_cost":"{2}{R}","cmc":3.0,"type_line":"Sorcery","colors":["R"],"keywords":{"NumDmg$":["1"],"SubAbility$":["DBToken"],"SpellDescription$":["CARDNAME deals 1 damage to any target. Create a 1/1 red Devil creature token. It has \"When this creature dies"," it deals 1 damage to any target.\""],"SP$":["DealDamage"],"ValidTgts$":["Creature","Player","Planeswalker"],"TgtPrompt$":["Select any target"]},"image_uris":{"normal":"https://img.scryfall.com/cards/normal/front/a/2/a2049072-5901-4edd-8305-ce55f256bca5.jpg?1576384624"}}
{"name":"Mercurial Geists","mana_cost":"{2}{U}{R}","cmc":4.0,"type_line":"Creature - Spirit","colors":["R","U"],"power":"1","toughness":"3","keywords":{"Mode$":["SpellCast"],"ValidActivatingPlayer$":["You"],"ValidCard$":["Instant","Sorcery"],"TriggerDescription$":["Whenever you cast an instant or sorcery spell"," CARDNAME gets +3/+0 until end of turn."],"TriggerZones$":["Battlefield"],"Execute$":["TrigPump"]},"image_uris":{"normal":"https://img.scryfall.com/cards/normal/front/8/a/8ab14779-7e79-449c-9a47-6ba219d0dbc5.jpg?1576385002"}}
{"name":"Mercurial Geists","mana_cost":"{2}{U}{R}","cmc":4.0,"type_line":"Creature - Spirit","colors":["R","U"],"power":"1","toughness":"3","keywords":{"Mode$":["SpellCast"],"ValidActivatingPlayer$":["You"],"ValidCard$":["Instant","Sorcery"],"TriggerDescription$":["Whenever you cast an instant or sorcery spell"," CARDNAME gets +3/+0 until end of turn."],"TriggerZones$":["Battlefield"],"Execute$":["TrigPump"]},"image_uris":{"normal":"https://img.scryfall.com/cards/normal/front/8/a/8ab14779-7e79-449c-9a47-6ba219d0dbc5.jpg?1576385002"}}
{"name":"Mountain","mana_cost":"","cmc":0.0,"type_line":"Basic Land - Mountain","colors":[],"keywords":{"PresentCompare$":["GE2"],"Mode$":["Phase"],"IsPresent$":["Permanent.Red+YouCtrl"],"Phase$":["Upkeep"],"TriggerDescription$":["At the beginning of each players upkeep"," that player may choose any number of tapped blue creatures they control and pay {4} for each creature chosen this way. If the player does"," untap those creatures."],"AB$":["Shuffle"],"SpellDescription$":["Shuffle your library. Activate this ability only if you control two or more red permanents."],"Defined$":["You"],"TriggerZones$":["Battlefield"],"Execute$":["TrigChoose"]},"image_uris":{"normal":"https://img.scryfall.com/cards/normal/front/d/c/dc3f4154-9347-4ceb-8744-9f1ace90d33f.jpg?1581482260"}}
{"name":"Mountain","mana_cost":"","cmc":0.0,"type_line":"Basic Land - Mountain","colors":[],"keywords":{"PresentCompare$":["GE2"],"Mode$":["Phase"],"IsPresent$":["Permanent.Red+YouCtrl"],"Phase$":["Upkeep"],"TriggerDescription$":["At the beginning of each players upkeep"," that player may choose any number of tapped blue creatures they control and pay {4} for each creature chosen this way. If the player does"," untap those creatures."],"AB$":["Shuffle"],"SpellDescription$":["Shuffle your library. Activate this ability only if you control two or more red permanents."],"Defined$":["You"],"TriggerZones$":["Battlefield"],"Execute$":["TrigChoose"]},"image_uris":{"normal":"https://img.scryfall.com/cards/normal/front/d/c/dc3f4154-9347-4ceb-8744-9f1ace90d33f.jpg?1581482260"}}
{"name":"Mountain","mana_cost":"","cmc":0.0,"type_line":"Basic Land - Mountain","colors":[],"keywords":{"PresentCompare$":["GE2"],"Mode$":["Phase"],"IsPresent$":["Permanent.Red+YouCtrl"],"Phase$":["Upkeep"],"TriggerDescription$":["At the beginning of each players upkeep"," that player may choose any number of tapped blue creatures they control and pay {4} for each creature chosen this way. If the player does"," untap those creatures."],"AB$":["Shuffle"],"SpellDescription$":["Shuffle your library. Activate this ability only if you control two or more red permanents."],"Defined$":["You"],"TriggerZones$":["Battlefield"],"Execute$":["TrigChoose"]},"image_uris":{"normal":"https://img.scryfall.com/cards/normal/front/d/c/dc3f4154-9347-4ceb-8744-9f1ace90d33f.jpg?1581482260"}}
{"name":"Mountain","mana_cost":"","cmc":0.0,"type_line":"Basic Land - Mountain","colors":[],"keywords":{"PresentCompare$":["GE2"],"Mode$":["Phase"],"IsPresent$":["Permanent.Red+YouCtrl"],"Phase$":["Upkeep"],"TriggerDescription$":["At the beginning of each players upkeep"," that player may choose any number of tapped blue creatures they control and pay {4} for each creature chosen this way. If the player does"," untap those creatures."],"AB$":["Shuffle"],"SpellDescription$":["Shuffle your library. Activate this ability only if you control two or more red permanents."],"Defined$":["You"],"TriggerZones$":["Battlefield"],"Execute$":["TrigChoose"]},"image_uris":{"normal":"https://img.scryfall.com/cards/normal/front/d/c/dc3f4154-9347-4ceb-8744-9f1ace90d33f.jpg?1581482260"}}
{"name":"Mountain","mana_cost":"","cmc":0.0,"type_line":"Basic Land - Mountain","colors":[],"keywords":{"PresentCompare$":["GE2"],"Mode$":["Phase"],"IsPresent$":["Permanent.Red+YouCtrl"],"Phase$":["Upkeep"],"TriggerDescription$":["At the beginning of each players upkeep"," that player may choose any number of tapped blue creatures they control and pay {4} for each creature chosen this way. If the player does"," untap those creatures."],"AB$":["Shuffle"],"SpellDescription$":["Shuffle your library. Activate this ability only if you control two or more red permanents."],"Defined$":["You"],"TriggerZones$":["Battlefield"],"Execute$":["TrigChoose"]},"image_uris":{"normal":"https://img.scryfall.com/cards/normal/front/d/c/dc3f4154-9347-4ceb-8744-9f1ace90d33f.jpg?1581482260"}}
{"name":"Mountain","mana_cost":"","cmc":0.0,"type_line":"Basic Land - Mountain","colors":[],"keywords":{"PresentCompare$":["GE2"],"Mode$":["Phase"],"IsPresent$":["Permanent.Red+YouCtrl"],"Phase$":["Upkeep"],"TriggerDescription$":["At the beginning of each players upkeep"," that player may choose any number of tapped blue creatures they control and pay {4} for each creature chosen this way. If the player does"," untap those creatures."],"AB$":["Shuffle"],"SpellDescription$":["Shuffle your library. Activate this ability only if you control two or more red permanents."],"Defined$":["You"],"TriggerZones$":["Battlefield"],"Execute$":["TrigChoose"]},"image_uris":{"normal":"https://img.scryfall.com/cards/normal/front/d/c/dc3f4154-9347-4ceb-8744-9f1ace90d33f.jpg?1581482260"}}
{"name":"Mountain","mana_cost":"","cmc":0.0,"type_line":"Basic Land - Mountain","colors":[],"keywords":{"PresentCompare$":["GE2"],"Mode$":["Phase"],"IsPresent$":["Permanent.Red+YouCtrl"],"Phase$":["Upkeep"],"TriggerDescription$":["At the beginning of each players upkeep"," that player may choose any number of tapped blue creatures they control and pay {4} for each creature chosen this way. If the player does"," untap those creatures."],"AB$":["Shuffle"],"SpellDescription$":["Shuffle your library. Activate this ability only if you control two or more red permanents."],"Defined$":["You"],"TriggerZones$":["Battlefield"],"Execute$":["TrigChoose"]},"image_uris":{"normal":"https://img.scryfall.com/cards/normal/front/d/c/dc3f4154-9347-4ceb-8744-9f1ace90d33f.jpg?1581482260"}}
{"name":"Mountain","mana_cost":"","cmc":0.0,"type_line":"Basic Land - Mountain","colors":[],"keywords":{"PresentCompare$":["GE2"],"Mode$":["Phase"],"IsPresent$":["Permanent.Red+YouCtrl"],"Phase$":["Upkeep"],"TriggerDescription$":["At the beginning of each players upkeep"," that player may choose any number of tapped blue creatures they control and pay {4} for each creature chosen this way. If the player does"," untap those creatures."],"AB$":["Shuffle"],"SpellDescription$":["Shuffle your library. Activate this ability only if you control two or more red permanents."],"Defined$":["You"],"TriggerZones$":["Battlefield"],"Execute$":["TrigChoose"]},"image_uris":{"normal":"https://img.scryfall.com/cards/normal/front/d/c/dc3f4154-9347-4ceb-8744-9f1ace90d33f.jpg?1581482260"}}
{"name":"Mountain","mana_cost":"","cmc":0.0,"type_line":"Basic Land - Mountain","colors":[],"keywords":{"PresentCompare$":["GE2"],"Mode$":["Phase"],"IsPresent$":["Permanent.Red+YouCtrl"],"Phase$":["Upkeep"],"TriggerDescription$":["At the beginning of each players upkeep"," that player may choose any number of tapped blue creatures they control and pay {4} for each creature chosen this way. If the player does"," untap those creatures."],"AB$":["Shuffle"],"SpellDescription$":["Shuffle your library. Activate this ability only if you control two or more red permanents."],"Defined$":["You"],"TriggerZones$":["Battlefield"],"Execute$":["TrigChoose"]},"image_uris":{"normal":"https://img.scryfall.com/cards/normal/front/d/c/dc3f4154-9347-4ceb-8744-9f1ace90d33f.jpg?1581482260"}}
{"name":"Mountain","mana_cost":"","cmc":0.0,"type_line":"Basic Land - Mountain","colors":[],"keywords":{"PresentCompare$":["GE2"],"Mode$":["Phase"],"IsPresent$":["Permanent.Red+YouCtrl"],"Phase$":["Upkeep"],"TriggerDescription$":["At the beginning of each players upkeep"," that player may choose any number of tapped blue creatures they control and pay {4} for each creature chosen this way. If the player does"," untap those creatures."],"AB$":["Shuffle"],"SpellDescription$":["Shuffle your library. Activate this ability only if you control two or more red permanents."],"Defined$":["You"],"TriggerZones$":["Battlefield"],"Execute$":["TrigChoose"]},"image_uris":{"normal":"https://img.scryfall.com/cards/normal/front/d/c/dc3f4154-9347-4ceb-8744-9f1ace90d33f.jpg?1581482260"}}
{"name":"Mountain","mana_cost":"","cmc":0.0,"type_line":"Basic Land - Mountain","colors":[],"keywords":{"PresentCompare$":["GE2"],"Mode$":["Phase"],"IsPresent$":["Permanent.Red+YouCtrl"],"Phase$":["Upkeep"],"TriggerDescription$":["At the beginning of each players upkeep"," that player may choose any number of tapped blue creatures they control and pay {4} for each creature chosen this way. If the player does"," untap those creatures."],"AB$":["Shuffle"],"SpellDescription$":["Shuffle your library. Activate this ability only if you control two or more red permanents."],"Defined$":["You"],"TriggerZones$":["Battlefield"],"Execute$":["TrigChoose"]},"image_uris":{"normal":"https://img.scryfall.com/cards/normal/front/d/c/dc3f4154-9347-4ceb-8744-9f1ace90d33f.jpg?1581482260"}}
{"name":"Mountain","mana_cost":"","cmc":0.0,"type_line":"Basic Land - Mountain","colors":[],"keywords":{"PresentCompare$":["GE2"],"Mode$":["Phase"],"IsPresent$":["Permanent.Red+YouCtrl"],"Phase$":["Upkeep"],"TriggerDescription$":["At the beginning of each players upkeep"," that player may choose any number of tapped blue creatures they control and pay {4} for each creature chosen this way. If the player does"," untap those creatures."],"AB$":["Shuffle"],"SpellDescription$":["Shuffle your library. Activate this ability only if you control two or more red permanents."],"Defined$":["You"],"TriggerZones$":["Battlefield"],"Execute$":["TrigChoose"]},"image_uris":{"normal":"https://img.scryfall.com/cards/normal/front/d/c/dc3f4154-9347-4ceb-8744-9f1ace90d33f.jpg?1581482260"}}
{"name":"Niblis of Dusk","mana_cost":"{2}{U}","cmc":3.0,"type_line":"Creature - Spirit","colors":["U"],"power":"2","toughness":"1","keywords":{},"image_uris":{"normal":"https://img.scryfall.com/cards/normal/front/3/9/394dd931-e34e-4314-88c9-774a2f3c8c1b.jpg?1576384160"}}
{"name":"Niblis of Frost","mana_cost":"{2}{U}{U}","cmc":4.0,"type_line":"Creature - Spirit","colors":["U"],"power":"3","toughness":"3","keywords":{"Mode$":["SpellCast"],"ValidActivatingPlayer$":["You"],"ValidCard$":["Instant","Sorcery"],"TriggerDescription$":["Whenever you cast an instant or sorcery spell"," tap target creature an opponent controls. That creature doesnt untap during its controllers next untap step."],"TriggerZones$":["Battlefield"],"Execute$":["TrigTap"]},"image_uris":{"normal":"https://img.scryfall.com/cards/normal/front/d/a/da2301c8-0ca8-4b26-a232-1df90effcb42.jpg?1576384202"}}
{"name":"Pieces of the Puzzle","mana_cost":"{2}{U}","cmc":3.0,"type_line":"Sorcery","colors":["U"],"keywords":{"Reveal$":["True"],"ChangeNum$":["2"],"ChangeValid$":["Instant","Sorcery"],"SpellDescription$":["Reveal the top five cards of your library. Put up to two instant and/or sorcery cards from among them into your hand and the rest into your graveyard."],"DigNum$":["5"],"Optional$":["True"],"SP$":["Dig"],"DestinationZone2$":["Graveyard"]},"image_uris":{"normal":"https://img.scryfall.com/cards/normal/front/6/9/69204c83-2e43-4ca1-a4cd-d75399a7d6dd.jpg?1576384174"}}
{"name":"Pore Over the Pages","mana_cost":"{3}{U}{U}","cmc":5.0,"type_line":"Sorcery","colors":["U"],"keywords":{"SubAbility$":["DBUntap"],"SpellDescription$":["Draw three cards"," untap up to two lands"," then discard a card."],"SP$":["Draw"],"NumCards$":["3"]},"image_uris":{"normal":"https://img.scryfall.com/cards/normal/front/b/2/b2288f7b-05b1-4a6c-8d02-42ffcadc6f0b.jpg?1576384182"}}
{"name":"Pyre Hound","mana_cost":"{3}{R}","cmc":4.0,"type_line":"Creature - Elemental Hound","colors":["R"],"power":"2","toughness":"3","keywords":{"Mode$":["SpellCast"],"ValidActivatingPlayer$":["You"],"ValidCard$":["Instant","Sorcery"],"TriggerDescription$":["Whenever you cast an instant or sorcery spell"," put a +1/+1 counter on CARDNAME."],"TriggerZones$":["Battlefield"],"Execute$":["DBPutCounter"]},"image_uris":{"normal":"https://img.scryfall.com/cards/normal/front/c/d/cd970484-49b3-442a-806a-cabc56526ee1.jpg?1562441175"}}
{"name":"Reduce to Ashes","mana_cost":"{4}{R}","cmc":5.0,"type_line":"Sorcery","colors":["R"],"keywords":{"NumDmg$":["5"],"SpellDescription$":["CARDNAME deals 5 damage to target creature or player. If that creature would die this turn"," exile it instead."],"SP$":["DealDamage"],"ReplaceDyingDefined$":["Targeted"],"ValidTgts$":["Creature"],"TgtPrompt$":["Select target creature"]},"image_uris":{"normal":"https://img.scryfall.com/cards/normal/front/f/e/fe580883-cdb1-4783-9feb-1e3bea83d209.jpg?1563899288"}}
{"name":"Rise from the Tides","mana_cost":"{5}{U}","cmc":6.0,"type_line":"Sorcery","colors":["U"],"keywords":{"SpellDescription$":["Create a tapped 2/2 black Zombie creature token for each instant and sorcery card in your graveyard."],"TokenScript$":["b_2_2_zombie"],"LegacyImage$":["b 2 2 zombie soi"],"SP$":["Token"],"TokenTapped$":["True"],"TokenOwner$":["You"],"TokenAmount$":["X"],"References$":["X"]},"image_uris":{"normal":"https://img.scryfall.com/cards/normal/front/c/d/cdbca952-b4e8-4833-aee3-7da8ae82906e.jpg?1547516468"}}
{"name":"Sanguinary Mage","mana_cost":"{1}{R}","cmc":2.0,"type_line":"Creature - Vampire Wizard","colors":["R"],"power":"1","toughness":"3","keywords":{},"image_uris":{"normal":"https://img.scryfall.com/cards/normal/front/a/c/ace86fac-769c-4440-9a40-318d7172555b.jpg?1576384883"}}
{"name":"Shreds of Sanity","mana_cost":"{2}{R}","cmc":3.0,"type_line":"Sorcery","colors":["R"],"keywords":{"Origin$":["Graveyard"],"SubAbility$":["DBReturn"],"SpellDescription$":["Return up to two target creature cards from your graveyard to your hand"," then discard a card."],"SP$":["ChangeZone"],"ValidTgts$":["Instant.YouCtrl"],"Destination$":["Hand"],"TgtPrompt$":["Choose target instant card in your graveyard"],"TargetMin$":["0"],"TargetMax$":["1"]},"image_uris":{"normal":"https://img.scryfall.com/cards/normal/front/7/8/782e5600-ac63-4f90-acbe-49c04d2840ee.jpg?1576384664"}}
{"name":"Shreds of Sanity","mana_cost":"{2}{R}","cmc":3.0,"type_line":"Sorcery","colors":["R"],"keywords":{"Origin$":["Graveyard"],"SubAbility$":["DBReturn"],"SpellDescription$":["Return up to two target creature cards from your graveyard to your hand"," then discard a card."],"SP$":["ChangeZone"],"ValidTgts$":["Instant.YouCtrl"],"Destination$":["Hand"],"TgtPrompt$":["Choose target instant card in your graveyard"],"TargetMin$":["0"],"TargetMax$":["1"]},"image_uris":{"normal":"https://img.scryfall.com/cards/normal/front/7/8/782e5600-ac63-4f90-acbe-49c04d2840ee.jpg?1576384664"}}
{"name":"Silburlind Snapper","mana_cost":"{5}{U}","cmc":6.0,"type_line":"Creature - Turtle","colors":["U"],"power":"6","toughness":"6","keywords":{},"image_uris":{"normal":"https://img.scryfall.com/cards/normal/front/d/7/d7347f4c-a4b3-4c71-91e5-699475e5926e.jpg?1576384224"}}
{"name":"Take Inventory","mana_cost":"{1}{U}","cmc":2.0,"type_line":"Sorcery","colors":["U"],"keywords":{"SubAbility$":["DBDraw"],"SpellDescription$":["Draw a card"," then draw cards equal to the number of cards named Take Inventory in your graveyard."],"Defined$":["You"],"SP$":["Draw"],"NumCards$":["1"]},"image_uris":{"normal":"https://img.scryfall.com/cards/normal/front/a/3/a3584150-4f09-4c15-b13e-707bd91b3004.jpg?1576384228"}}
{"name":"Take Inventory","mana_cost":"{1}{U}","cmc":2.0,"type_line":"Sorcery","colors":["U"],"keywords":{"SubAbility$":["DBDraw"],"SpellDescription$":["Draw a card"," then draw cards equal to the number of cards named Take Inventory in your graveyard."],"Defined$":["You"],"SP$":["Draw"],"NumCards$":["1"]},"image_uris":{"normal":"https://img.scryfall.com/cards/normal/front/a/3/a3584150-4f09-4c15-b13e-707bd91b3004.jpg?1576384228"}}
{"name":"Take Inventory","mana_cost":"{1}{U}","cmc":2.0,"type_line":"Sorcery","colors":["U"],"keywords":{"SubAbility$":["DBDraw"],"SpellDescription$":["Draw a card"," then draw cards equal to the number of cards named Take Inventory in your graveyard."],"Defined$":["You"],"SP$":["Draw"],"NumCards$":["1"]},"image_uris":{"normal":"https://img.scryfall.com/cards/normal/front/a/3/a3584150-4f09-4c15-b13e-707bd91b3004.jpg?1576384228"}}
{"name":"Thermo-Alchemist","mana_cost":"{1}{R}","cmc":2.0,"type_line":"Creature - Human Shaman","colors":["R"],"power":"0","toughness":"3","keywords":{},"image_uris":{"normal":"https://img.scryfall.com/cards/normal/front/c/9/c9cac6a6-ded0-47cb-88d2-8838db9cc6b2.jpg?1547517429"}}
{"name":"Thermo-Alchemist","mana_cost":"{1}{R}","cmc":2.0,"type_line":"Creature - Human Shaman","colors":["R"],"power":"0","toughness":"3","keywords":{},"image_uris":{"normal":"https://img.scryfall.com/cards/normal/front/c/9/c9cac6a6-ded0-47cb-88d2-8838db9cc6b2.jpg?1547517429"}}
{"name":"Turn Aside","mana_cost":"{U}","cmc":1.0,"type_line":"Instant","colors":["U"],"keywords":{"SpellDescription$":["Counter target spell that targets a permanent you control."],"SP$":["Counter"],"TargetValidTargeting$":["Permanent.YouCtrl+inZoneBattlefield"],"TargetType$":["Spell"],"ValidTgts$":["Card"],"TgtPrompt$":["Select target spell"]},"image_uris":{"normal":"https://img.scryfall.com/cards/normal/front/3/b/3b7573c2-484c-4b4e-9c26-0f005bd1daee.jpg?1576384240"}}
{"name":"Weaver of Lightning","mana_cost":"{2}{R}","cmc":3.0,"type_line":"Creature - Human Shaman","colors":["R"],"power":"1","toughness":"4","keywords":{"Mode$":["SpellCast"],"ValidActivatingPlayer$":["You"],"ValidCard$":["Instant","Sorcery"],"TriggerDescription$":["Whenever you cast an instant or sorcery spell"," CARDNAME deals 1 damage to target creature an opponent controls."],"TriggerZones$":["Battlefield"],"Execute$":["TrigDealDamage"]},"image_uris":{"normal":"https://img.scryfall.com/cards/normal/front/b/a/ba1e6885-dca0-4a4b-abb8-0f32680f618d.jpg?1576384728"}}
{"name":"Weaver of Lightning","mana_cost":"{2}{R}","cmc":3.0,"type_line":"Creature - Human Shaman","colors":["R"],"power":"1","toughness":"4","keywords":{"Mode$":["SpellCast"],"ValidActivatingPlayer$":["You"],"ValidCard$":["Instant","Sorcery"],"TriggerDescription$":["Whenever you cast an instant or sorcery spell"," CARDNAME deals 1 damage to target creature an opponent controls."],"TriggerZones$":["Battlefield"],"Execute$":["TrigDealDamage"]},"image_uris":{"normal":"https://img.scryfall.com/cards/normal/front/b/a/ba1e6885-dca0-4a4b-abb8-0f32680f618d.jpg?1576384728"}}
