{"name":"Bladed Pinions","mana_cost":"{2}","cmc":2.0,"type_line":"Artifact - Equipment","colors":[],"keywords":{},"image_uris":{"normal":"https://img.scryfall.com/cards/normal/front/b/f/bf479c90-c791-4152-a8e6-fd3123f698df.jpg?1562822572"}}
{"name":"Bladed Pinions","mana_cost":"{2}","cmc":2.0,"type_line":"Artifact - Equipment","colors":[],"keywords":{},"image_uris":{"normal":"https://img.scryfall.com/cards/normal/front/b/f/bf479c90-c791-4152-a8e6-fd3123f698df.jpg?1562822572"}}
{"name":"Heavy Arbalest","mana_cost":"{3}","cmc":3.0,"type_line":"Artifact - Equipment","colors":[],"keywords":{},"image_uris":{"normal":"https://img.scryfall.com/cards/normal/front/8/1/813fae24-ff38-45e8-8ab9-d539d4494435.jpg?1562437533"}}
{"name":"Strider Harness","mana_cost":"{3}","cmc":3.0,"type_line":"Artifact - Equipment","colors":[],"keywords":{},"image_uris":{"normal":"https://img.scryfall.com/cards/normal/front/5/e/5e94daa9-5b9b-4fd2-829e-081eed22c18f.jpg?1555041055"}}
{"name":"Corpse Cur","mana_cost":"{4}","cmc":4.0,"type_line":"Artifact Creature - Hound","colors":[],"power":"2","toughness":"2","keywords":{"Mode$":["ChangesZone"],"ValidCard$":["Card.Self"],"Origin$":["Any"],"OptionalDecider$":["You"],"TriggerDescription$":["When CARDNAME enters the battlefield"," you may return target creature card with infect from your graveyard to your hand."],"Destination$":["Battlefield"],"Execute$":["TrigReturn"]},"image_uris":{"normal":"https://img.scryfall.com/cards/normal/front/9/c/9c6e19a1-b9ea-4724-96d6-63c4b4967257.jpg?1562820894"}}
{"name":"Corpse Cur","mana_cost":"{4}","cmc":4.0,"type_line":"Artifact Creature - Hound","colors":[],"power":"2","toughness":"2","keywords":{"Mode$":["ChangesZone"],"ValidCard$":["Card.Self"],"Origin$":["Any"],"OptionalDecider$":["You"],"TriggerDescription$":["When CARDNAME enters the battlefield"," you may return target creature card with infect from your graveyard to your hand."],"Destination$":["Battlefield"],"Execute$":["TrigReturn"]},"image_uris":{"normal":"https://img.scryfall.com/cards/normal/front/9/c/9c6e19a1-b9ea-4724-96d6-63c4b4967257.jpg?1562820894"}}
{"name":"Ichorclaw Myr","mana_cost":"{2}","cmc":2.0,"type_line":"Artifact Creature - Myr","colors":[],"power":"1","toughness":"1","keywords":{"Mode$":["AttackerBlocked"],"ValidCard$":["Card.Self"],"TriggerDescription$":["Whenever CARDNAME becomes blocked"," it gets +2/+2 until end of turn."],"Execute$":["TrigPump"]},"image_uris":{"normal":"https://img.scryfall.com/cards/normal/front/f/a/faef8b8b-2c45-4fed-b6ba-a8ac49c66330.jpg?1562825404"}}
{"name":"Ichorclaw Myr","mana_cost":"{2}","cmc":2.0,"type_line":"Artifact Creature - Myr","colors":[],"power":"1","toughness":"1","keywords":{"Mode$":["AttackerBlocked"],"ValidCard$":["Card.Self"],"TriggerDescription$":["Whenever CARDNAME becomes blocked"," it gets +2/+2 until end of turn."],"Execute$":["TrigPump"]},"image_uris":{"normal":"https://img.scryfall.com/cards/normal/front/f/a/faef8b8b-2c45-4fed-b6ba-a8ac49c66330.jpg?1562825404"}}
{"name":"Ichorclaw Myr","mana_cost":"{2}","cmc":2.0,"type_line":"Artifact Creature - Myr","colors":[],"power":"1","toughness":"1","keywords":{"Mode$":["AttackerBlocked"],"ValidCard$":["Card.Self"],"TriggerDescription$":["Whenever CARDNAME becomes blocked"," it gets +2/+2 until end of turn."],"Execute$":["TrigPump"]},"image_uris":{"normal":"https://img.scryfall.com/cards/normal/front/f/a/faef8b8b-2c45-4fed-b6ba-a8ac49c66330.jpg?1562825404"}}
{"name":"Necropede","mana_cost":"{2}","cmc":2.0,"type_line":"Artifact Creature - Insect","colors":[],"power":"1","toughness":"1","keywords":{"Mode$":["ChangesZone"],"ValidCard$":["Card.Self"],"Origin$":["Battlefield"],"OptionalDecider$":["TriggeredCardController"],"TriggerDescription$":["When CARDNAME dies"," you may put a -1/-1 counter on target creature."],"Destination$":["Graveyard"],"Execute$":["TrigPutCounter"],"TriggerController$":["TriggeredCardController"]},"image_uris":{"normal":"https://img.scryfall.com/cards/normal/front/8/d/8d2e522b-e6f8-4fae-8c08-ce2bb8bed04f.jpg?1562820181"}}
{"name":"Necropede","mana_cost":"{2}","cmc":2.0,"type_line":"Artifact Creature - Insect","colors":[],"power":"1","toughness":"1","keywords":{"Mode$":["ChangesZone"],"ValidCard$":["Card.Self"],"Origin$":["Battlefield"],"OptionalDecider$":["TriggeredCardController"],"TriggerDescription$":["When CARDNAME dies"," you may put a -1/-1 counter on target creature."],"Destination$":["Graveyard"],"Execute$":["TrigPutCounter"],"TriggerController$":["TriggeredCardController"]},"image_uris":{"normal":"https://img.scryfall.com/cards/normal/front/8/d/8d2e522b-e6f8-4fae-8c08-ce2bb8bed04f.jpg?1562820181"}}
{"name":"Forest","mana_cost":"","cmc":0.0,"type_line":"Basic Land - Forest","colors":[],"keywords":{},"image_uris":{"normal":"https://img.scryfall.com/cards/normal/front/c/4/c4be31c4-9cb3-4a07-865b-5621127df660.jpg?1581482262"}}
{"name":"Forest","mana_cost":"","cmc":0.0,"type_line":"Basic Land - Forest","colors":[],"keywords":{},"image_uris":{"normal":"https://img.scryfall.com/cards/normal/front/c/4/c4be31c4-9cb3-4a07-865b-5621127df660.jpg?1581482262"}}
{"name":"Forest","mana_cost":"","cmc":0.0,"type_line":"Basic Land - Forest","colors":[],"keywords":{},"image_uris":{"normal":"https://img.scryfall.com/cards/normal/front/c/4/c4be31c4-9cb3-4a07-865b-5621127df660.jpg?1581482262"}}
{"name":"Forest","mana_cost":"","cmc":0.0,"type_line":"Basic Land - Forest","colors":[],"keywords":{},"image_uris":{"normal":"https://img.scryfall.com/cards/normal/front/c/4/c4be31c4-9cb3-4a07-865b-5621127df660.jpg?1581482262"}}
{"name":"Forest","mana_cost":"","cmc":0.0,"type_line":"Basic Land - Forest","colors":[],"keywords":{},"image_uris":{"normal":"https://img.scryfall.com/cards/normal/front/c/4/c4be31c4-9cb3-4a07-865b-5621127df660.jpg?1581482262"}}
{"name":"Forest","mana_cost":"","cmc":0.0,"type_line":"Basic Land - Forest","colors":[],"keywords":{},"image_uris":{"normal":"https://img.scryfall.com/cards/normal/front/c/4/c4be31c4-9cb3-4a07-865b-5621127df660.jpg?1581482262"}}
{"name":"Forest","mana_cost":"","cmc":0.0,"type_line":"Basic Land - Forest","colors":[],"keywords":{},"image_uris":{"normal":"https://img.scryfall.com/cards/normal/front/c/4/c4be31c4-9cb3-4a07-865b-5621127df660.jpg?1581482262"}}
{"name":"Forest","mana_cost":"","cmc":0.0,"type_line":"Basic Land - Forest","colors":[],"keywords":{},"image_uris":{"normal":"https://img.scryfall.com/cards/normal/front/c/4/c4be31c4-9cb3-4a07-865b-5621127df660.jpg?1581482262"}}
{"name":"Forest","mana_cost":"","cmc":0.0,"type_line":"Basic Land - Forest","colors":[],"keywords":{},"image_uris":{"normal":"https://img.scryfall.com/cards/normal/front/c/4/c4be31c4-9cb3-4a07-865b-5621127df660.jpg?1581482262"}}
{"name":"Forest","mana_cost":"","cmc":0.0,"type_line":"Basic Land - Forest","colors":[],"keywords":{},"image_uris":{"normal":"https://img.scryfall.com/cards/normal/front/c/4/c4be31c4-9cb3-4a07-865b-5621127df660.jpg?1581482262"}}
{"name":"Forest","mana_cost":"","cmc":0.0,"type_line":"Basic Land - Forest","colors":[],"keywords":{},"image_uris":{"normal":"https://img.scryfall.com/cards/normal/front/c/4/c4be31c4-9cb3-4a07-865b-5621127df660.jpg?1581482262"}}
{"name":"Forest","mana_cost":"","cmc":0.0,"type_line":"Basic Land - Forest","colors":[],"keywords":{},"image_uris":{"normal":"https://img.scryfall.com/cards/normal/front/c/4/c4be31c4-9cb3-4a07-865b-5621127df660.jpg?1581482262"}}
{"name":"Forest","mana_cost":"","cmc":0.0,"type_line":"Basic Land - Forest","colors":[],"keywords":{},"image_uris":{"normal":"https://img.scryfall.com/cards/normal/front/c/4/c4be31c4-9cb3-4a07-865b-5621127df660.jpg?1581482262"}}
{"name":"Swamp","mana_cost":"","cmc":0.0,"type_line":"Basic Land - Swamp","colors":[],"keywords":{},"image_uris":{"normal":"https://img.scryfall.com/cards/normal/front/6/6/66bb5192-58bc-4efe-a145-2e804fd3483d.jpg?1581481510"}}
{"name":"Swamp","mana_cost":"","cmc":0.0,"type_line":"Basic Land - Swamp","colors":[],"keywords":{},"image_uris":{"normal":"https://img.scryfall.com/cards/normal/front/6/6/66bb5192-58bc-4efe-a145-2e804fd3483d.jpg?1581481510"}}
{"name":"Swamp","mana_cost":"","cmc":0.0,"type_line":"Basic Land - Swamp","colors":[],"keywords":{},"image_uris":{"normal":"https://img.scryfall.com/cards/normal/front/6/6/66bb5192-58bc-4efe-a145-2e804fd3483d.jpg?1581481510"}}
{"name":"Swamp","mana_cost":"","cmc":0.0,"type_line":"Basic Land - Swamp","colors":[],"keywords":{},"image_uris":{"normal":"https://img.scryfall.com/cards/normal/front/6/6/66bb5192-58bc-4efe-a145-2e804fd3483d.jpg?1581481510"}}
{"name":"Swamp","mana_cost":"","cmc":0.0,"type_line":"Basic Land - Swamp","colors":[],"keywords":{},"image_uris":{"normal":"https://img.scryfall.com/cards/normal/front/6/6/66bb5192-58bc-4efe-a145-2e804fd3483d.jpg?1581481510"}}
{"name":"Swamp","mana_cost":"","cmc":0.0,"type_line":"Basic Land - Swamp","colors":[],"keywords":{},"image_uris":{"normal":"https://img.scryfall.com/cards/normal/front/6/6/66bb5192-58bc-4efe-a145-2e804fd3483d.jpg?1581481510"}}
{"name":"Swamp","mana_cost":"","cmc":0.0,"type_line":"Basic Land - Swamp","colors":[],"keywords":{},"image_uris":{"normal":"https://img.scryfall.com/cards/normal/front/6/6/66bb5192-58bc-4efe-a145-2e804fd3483d.jpg?1581481510"}}
{"name":"Swamp","mana_cost":"","cmc":0.0,"type_line":"Basic Land - Swamp","colors":[],"keywords":{},"image_uris":{"normal":"https://img.scryfall.com/cards/normal/front/6/6/66bb5192-58bc-4efe-a145-2e804fd3483d.jpg?1581481510"}}
{"name":"Swamp","mana_cost":"","cmc":0.0,"type_line":"Basic Land - Swamp","colors":[],"keywords":{},"image_uris":{"normal":"https://img.scryfall.com/cards/normal/front/6/6/66bb5192-58bc-4efe-a145-2e804fd3483d.jpg?1581481510"}}
{"name":"Swamp","mana_cost":"","cmc":0.0,"type_line":"Basic Land - Swamp","colors":[],"keywords":{},"image_uris":{"normal":"https://img.scryfall.com/cards/normal/front/6/6/66bb5192-58bc-4efe-a145-2e804fd3483d.jpg?1581481510"}}
{"name":"Swamp","mana_cost":"","cmc":0.0,"type_line":"Basic Land - Swamp","colors":[],"keywords":{},"image_uris":{"normal":"https://img.scryfall.com/cards/normal/front/6/6/66bb5192-58bc-4efe-a145-2e804fd3483d.jpg?1581481510"}}
{"name":"Swamp","mana_cost":"","cmc":0.0,"type_line":"Basic Land - Swamp","colors":[],"keywords":{},"image_uris":{"normal":"https://img.scryfall.com/cards/normal/front/6/6/66bb5192-58bc-4efe-a145-2e804fd3483d.jpg?1581481510"}}
{"name":"Swamp","mana_cost":"","cmc":0.0,"type_line":"Basic Land - Swamp","colors":[],"keywords":{},"image_uris":{"normal":"https://img.scryfall.com/cards/normal/front/6/6/66bb5192-58bc-4efe-a145-2e804fd3483d.jpg?1581481510"}}
{"name":"Blackcleave Goblin","mana_cost":"{3}{B}","cmc":4.0,"type_line":"Creature - Goblin Zombie","colors":["B"],"power":"2","toughness":"1","keywords":{},"image_uris":{"normal":"https://img.scryfall.com/cards/normal/front/9/5/95986875-59f5-414f-867f-94f30cefa5d6.jpg?1562820574"}}
{"name":"Contagious Nim","mana_cost":"{2}{B}","cmc":3.0,"type_line":"Creature - Zombie","colors":["B"],"power":"2","toughness":"2","keywords":{},"image_uris":{"normal":"https://img.scryfall.com/cards/normal/front/e/8/e83a9dea-2aa1-48cd-afe2-f98057b95f6e.jpg?1562824519"}}
{"name":"Cystbearer","mana_cost":"{2}{G}","cmc":3.0,"type_line":"Creature - Beast","colors":["G"],"power":"2","toughness":"3","keywords":{},"image_uris":{"normal":"https://img.scryfall.com/cards/normal/front/b/6/b6c10302-f0b3-4076-ae5c-a8c8c09a7d41.jpg?1562822162"}}
{"name":"Cystbearer","mana_cost":"{2}{G}","cmc":3.0,"type_line":"Creature - Beast","colors":["G"],"power":"2","toughness":"3","keywords":{},"image_uris":{"normal":"https://img.scryfall.com/cards/normal/front/b/6/b6c10302-f0b3-4076-ae5c-a8c8c09a7d41.jpg?1562822162"}}
{"name":"Hand of the Praetors","mana_cost":"{3}{B}","cmc":4.0,"type_line":"Creature - Zombie","colors":["B"],"power":"3","toughness":"2","keywords":{"Mode$":["SpellCast"],"ValidActivatingPlayer$":["You"],"ValidCard$":["Card.withInfect"],"TriggerDescription$":["Whenever you cast a spell with infect"," target player gets a poison counter."],"TriggerZones$":["Battlefield"],"Execute$":["TrigPoison"]},"image_uris":{"normal":"https://img.scryfall.com/cards/normal/front/9/4/94ca493e-f09b-4b11-bb47-0562dfc203ca.jpg?1562820548"}}
{"name":"Ichor Rats","mana_cost":"{1}{B}{B}","cmc":3.0,"type_line":"Creature - Rat","colors":["B"],"power":"2","toughness":"1","keywords":{"Mode$":["ChangesZone"],"ValidCard$":["Card.Self"],"Origin$":["Any"],"TriggerDescription$":["When CARDNAME enters the battlefield"," each player gets a poison counter."],"Destination$":["Battlefield"],"Execute$":["TrigPoison"]},"image_uris":{"normal":"https://img.scryfall.com/cards/normal/front/2/0/2013aed6-7415-4bf0-a3bb-46d6beecbaff.jpg?1562815353"}}
{"name":"Ichor Rats","mana_cost":"{1}{B}{B}","cmc":3.0,"type_line":"Creature - Rat","colors":["B"],"power":"2","toughness":"1","keywords":{"Mode$":["ChangesZone"],"ValidCard$":["Card.Self"],"Origin$":["Any"],"TriggerDescription$":["When CARDNAME enters the battlefield"," each player gets a poison counter."],"Destination$":["Battlefield"],"Execute$":["TrigPoison"]},"image_uris":{"normal":"https://img.scryfall.com/cards/normal/front/2/0/2013aed6-7415-4bf0-a3bb-46d6beecbaff.jpg?1562815353"}}
{"name":"Plague Stinger","mana_cost":"{1}{B}","cmc":2.0,"type_line":"Creature - Insect Horror","colors":["B"],"power":"1","toughness":"1","keywords":{},"image_uris":{"normal":"https://img.scryfall.com/cards/normal/front/a/a/aae856bc-f65f-42ba-9344-1a30b356c041.jpg?1562821570"}}
{"name":"Plague Stinger","mana_cost":"{1}{B}","cmc":2.0,"type_line":"Creature - Insect Horror","colors":["B"],"power":"1","toughness":"1","keywords":{},"image_uris":{"normal":"https://img.scryfall.com/cards/normal/front/a/a/aae856bc-f65f-42ba-9344-1a30b356c041.jpg?1562821570"}}
{"name":"Plague Stinger","mana_cost":"{1}{B}","cmc":2.0,"type_line":"Creature - Insect Horror","colors":["B"],"power":"1","toughness":"1","keywords":{},"image_uris":{"normal":"https://img.scryfall.com/cards/normal/front/a/a/aae856bc-f65f-42ba-9344-1a30b356c041.jpg?1562821570"}}
{"name":"Putrefax","mana_cost":"{3}{G}{G}","cmc":5.0,"type_line":"Creature - Horror","colors":["G"],"power":"5","toughness":"3","keywords":{"Mode$":["Phase"],"Phase$":["End of Turn"],"TriggerDescription$":["At the beginning of the end step"," sacrifice CARDNAME."],"TriggerZones$":["Battlefield"],"Execute$":["TrigSac"]},"image_uris":{"normal":"https://img.scryfall.com/cards/normal/front/b/2/b2b2c3f9-a831-4fd2-80e8-b67b0df3e98b.jpg?1562821947"}}
{"name":"Tangle Angler","mana_cost":"{3}{G}","cmc":4.0,"type_line":"Creature - Horror","colors":["G"],"power":"1","toughness":"5","keywords":{"AB$":["MustBlock"],"SpellDescription$":["Target creature blocks CARDNAME this turn if able."],"ValidTgts$":["Creature"],"TgtPrompt$":["Select target creature"],"AILogic$":["AllowNonLethal"]},"image_uris":{"normal":"https://img.scryfall.com/cards/normal/front/b/6/b678bd68-e866-4081-95f9-2bd93a84d400.jpg?1562822150"}}
{"name":"Tangle Angler","mana_cost":"{3}{G}","cmc":4.0,"type_line":"Creature - Horror","colors":["G"],"power":"1","toughness":"5","keywords":{"AB$":["MustBlock"],"SpellDescription$":["Target creature blocks CARDNAME this turn if able."],"ValidTgts$":["Creature"],"TgtPrompt$":["Select target creature"],"AILogic$":["AllowNonLethal"]},"image_uris":{"normal":"https://img.scryfall.com/cards/normal/front/b/6/b678bd68-e866-4081-95f9-2bd93a84d400.jpg?1562822150"}}
{"name":"Relic Putrescence","mana_cost":"{2}{B}","cmc":3.0,"type_line":"Enchantment - Aura","colors":["B"],"keywords":{"Mode$":["Taps"],"ValidCard$":["Card.AttachedBy"],"TriggerDescription$":["Whenever enchanted artifact becomes tapped"," its controller gets a poison counter."],"SP$":["Attach"],"TriggerZones$":["Battlefield"],"ValidTgts$":["Artifact"],"AILogic$":["Curse"],"Execute$":["TrigPoison"]},"image_uris":{"normal":"https://img.scryfall.com/cards/normal/front/c/a/ca940b4e-6f5e-4492-b6e0-dbf619eddadd.jpg?1562823021"}}
{"name":"Carrion Call","mana_cost":"{3}{G}","cmc":4.0,"type_line":"Instant","colors":["G"],"keywords":{"SpellDescription$":["Create two 1/1 green Insect creature tokens with infect."],"TokenScript$":["g_1_1_insect_infect"],"LegacyImage$":["g 1 1 insect infect som"],"SP$":["Token"],"TokenOwner$":["You"],"TokenAmount$":["2"]},"image_uris":{"normal":"https://img.scryfall.com/cards/normal/front/b/c/bc3c1a8e-3bdb-42cf-9442-5de7e4670d66.jpg?1562822445"}}
{"name":"Carrion Call","mana_cost":"{3}{G}","cmc":4.0,"type_line":"Instant","colors":["G"],"keywords":{"SpellDescription$":["Create two 1/1 green Insect creature tokens with infect."],"TokenScript$":["g_1_1_insect_infect"],"LegacyImage$":["g 1 1 insect infect som"],"SP$":["Token"],"TokenOwner$":["You"],"TokenAmount$":["2"]},"image_uris":{"normal":"https://img.scryfall.com/cards/normal/front/b/c/bc3c1a8e-3bdb-42cf-9442-5de7e4670d66.jpg?1562822445"}}
{"name":"Giant Growth","mana_cost":"{G}","cmc":1.0,"type_line":"Instant","colors":["G"],"keywords":{"SpellDescription$":["Target creature gets +3/+3 until end of turn."],"NumAtt$":["+3"],"SP$":["Pump"],"NumDef$":["+3"],"ValidTgts$":["Creature"],"TgtPrompt$":["Select target creature"]},"image_uris":{"normal":"https://img.scryfall.com/cards/normal/front/0/6/06ec9e8b-4bd8-4caf-a559-6514b7ab4ca4.jpg?1557576917"}}
{"name":"Giant Growth","mana_cost":"{G}","cmc":1.0,"type_line":"Instant","colors":["G"],"keywords":{"SpellDescription$":["Target creature gets +3/+3 until end of turn."],"NumAtt$":["+3"],"SP$":["Pump"],"NumDef$":["+3"],"ValidTgts$":["Creature"],"TgtPrompt$":["Select target creature"]},"image_uris":{"normal":"https://img.scryfall.com/cards/normal/front/0/6/06ec9e8b-4bd8-4caf-a559-6514b7ab4ca4.jpg?1557576917"}}
{"name":"Slice in Twain","mana_cost":"{2}{G}{G}","cmc":4.0,"type_line":"Instant","colors":["G"],"keywords":{"SubAbility$":["DBDraw"],"SpellDescription$":["Destroy target artifact or enchantment."],"SP$":["Destroy"],"ValidTgts$":["Artifact","Enchantment"],"TgtPrompt$":["Select target artifact or enchantment"]},"image_uris":{"normal":"https://img.scryfall.com/cards/normal/front/d/7/d7129e47-f502-4df6-b21c-5713c3f8c775.jpg?1568004666"}}
{"name":"Slice in Twain","mana_cost":"{2}{G}{G}","cmc":4.0,"type_line":"Instant","colors":["G"],"keywords":{"SubAbility$":["DBDraw"],"SpellDescription$":["Destroy target artifact or enchantment."],"SP$":["Destroy"],"ValidTgts$":["Artifact","Enchantment"],"TgtPrompt$":["Select target artifact or enchantment"]},"image_uris":{"normal":"https://img.scryfall.com/cards/normal/front/d/7/d7129e47-f502-4df6-b21c-5713c3f8c775.jpg?1568004666"}}
{"name":"Assassinate","mana_cost":"{2}{B}","cmc":3.0,"type_line":"Sorcery","colors":["B"],"keywords":{"SpellDescription$":["Destroy target tapped creature."],"SP$":["Destroy"],"ValidTgts$":["Creature.tapped"],"TgtPrompt$":["Select target tapped creature"]},"image_uris":{"normal":"https://img.scryfall.com/cards/normal/front/3/6/369521a4-0635-420f-81c3-352b2147974b.jpg?1562906006"}}
{"name":"Assassinate","mana_cost":"{2}{B}","cmc":3.0,"type_line":"Sorcery","colors":["B"],"keywords":{"SpellDescription$":["Destroy target tapped creature."],"SP$":["Destroy"],"ValidTgts$":["Creature.tapped"],"TgtPrompt$":["Select target tapped creature"]},"image_uris":{"normal":"https://img.scryfall.com/cards/normal/front/3/6/369521a4-0635-420f-81c3-352b2147974b.jpg?1562906006"}}
{"name":"Rise from the Grave","mana_cost":"{4}{B}","cmc":5.0,"type_line":"Sorcery","colors":["B"],"keywords":{"Origin$":["Graveyard"],"SubAbility$":["Animate"],"SpellDescription$":["Put target creature card from a graveyard onto the battlefield under your control. That creature is a black Zombie in addition to its other colors and types."],"GainControl$":["True"],"SP$":["ChangeZone"],"ValidTgts$":["Creature"],"Destination$":["Battlefield"],"TgtPrompt$":["Choose target creature card in a graveyard"]},"image_uris":{"normal":"https://img.scryfall.com/cards/normal/front/b/c/bc73644e-884c-47cd-aeec-ab80360dd5ae.jpg?1562303908"}}
