{"name":"Drowner Initiate","mana_cost":"{U}","cmc":1.0,"type_line":"Creature - Merfolk Wizard","colors":["U"],"power":"1","toughness":"1","keywords":{"Mode$":["SpellCast"],"ValidCard$":["Card.Blue"],"OptionalDecider$":["You"],"TriggerDescription$":["Whenever a player casts a blue spell"," you may pay {1}. If you do"," target player puts the top two cards of their library into their graveyard."],"TriggerZones$":["Battlefield"],"Execute$":["TrigMill"]},"image_uris":{"normal":"https://img.scryfall.com/cards/normal/front/2/8/28accc5f-63a5-47d0-b0e6-747aa0aa43e5.jpg?1562828075"}}
{"name":"Nurturer Initiate","mana_cost":"{G}","cmc":1.0,"type_line":"Creature - Elf Shaman","colors":["G"],"power":"1","toughness":"1","keywords":{"Mode$":["SpellCast"],"ValidCard$":["Card.Green"],"TriggerDescription$":["Whenever a player casts a green spell"," you may pay {1}. If you do"," target creature gets +1/+1 until end of turn."],"TriggerZones$":["Battlefield"],"Execute$":["TrigPump"]},"image_uris":{"normal":"https://img.scryfall.com/cards/normal/front/2/3/2330c78d-1655-4074-a650-27740be4cee1.jpg?1562827868"}}
{"name":"Nurturer Initiate","mana_cost":"{G}","cmc":1.0,"type_line":"Creature - Elf Shaman","colors":["G"],"power":"1","toughness":"1","keywords":{"Mode$":["SpellCast"],"ValidCard$":["Card.Green"],"TriggerDescription$":["Whenever a player casts a green spell"," you may pay {1}. If you do"," target creature gets +1/+1 until end of turn."],"TriggerZones$":["Battlefield"],"Execute$":["TrigPump"]},"image_uris":{"normal":"https://img.scryfall.com/cards/normal/front/2/3/2330c78d-1655-4074-a650-27740be4cee1.jpg?1562827868"}}
{"name":"Trip Noose","mana_cost":"{2}","cmc":2.0,"type_line":"Artifact","colors":[],"keywords":{"AB$":["Tap"],"SpellDescription$":["Tap target creature."],"ValidTgts$":["Creature"],"TgtPrompt$":["Select target creature"]},"image_uris":{"normal":"https://img.scryfall.com/cards/normal/front/a/c/ac039d9a-d248-497f-ac84-16ccc568f283.jpg?1562270251"}}
{"name":"Slippery Bogle","mana_cost":"{G/U}","cmc":1.0,"type_line":"Creature - Beast","colors":["G","U"],"power":"1","toughness":"1","keywords":{},"image_uris":{"normal":"https://img.scryfall.com/cards/normal/front/c/4/c4e4bbea-7e3f-4de0-bb01-dfd67f21c254.jpg?1547518325"}}
{"name":"Merrow Levitator","mana_cost":"{3}{U}","cmc":4.0,"type_line":"Creature - Merfolk Wizard","colors":["U"],"power":"2","toughness":"3","keywords":{"Mode$":["SpellCast"],"ValidActivatingPlayer$":["You"],"ValidCard$":["Card.Blue"],"OptionalDecider$":["You"],"TriggerDescription$":["Whenever you cast a blue spell"," you may untap CARDNAME."],"AB$":["Pump"],"SpellDescription$":["Target creature gains flying until end of turn."],"TriggerZones$":["Battlefield"],"KW$":["Flying"],"ValidTgts$":["Creature"],"TgtPrompt$":["Select target creature"],"Execute$":["TrigUntap"]},"image_uris":{"normal":"https://img.scryfall.com/cards/normal/front/e/2/e2b2f122-0406-44f4-82b0-9f46b52e7d99.jpg?1562942834"}}
{"name":"Nettle Sentinel","mana_cost":"{G}","cmc":1.0,"type_line":"Creature - Elf Warrior","colors":["G"],"power":"2","toughness":"2","keywords":{"Mode$":["SpellCast"],"ValidActivatingPlayer$":["You"],"ValidCard$":["Card.Green"],"OptionalDecider$":["You"],"TriggerDescription$":["Whenever you cast a green spell"," you may untap CARDNAME."],"TriggerZones$":["Battlefield"],"Execute$":["TrigUntap"]},"image_uris":{"normal":"https://img.scryfall.com/cards/normal/front/3/f/3f290ed2-d1a8-4a90-a3a7-8240652dc109.jpg?1562434953"}}
{"name":"Nettle Sentinel","mana_cost":"{G}","cmc":1.0,"type_line":"Creature - Elf Warrior","colors":["G"],"power":"2","toughness":"2","keywords":{"Mode$":["SpellCast"],"ValidActivatingPlayer$":["You"],"ValidCard$":["Card.Green"],"OptionalDecider$":["You"],"TriggerDescription$":["Whenever you cast a green spell"," you may untap CARDNAME."],"TriggerZones$":["Battlefield"],"Execute$":["TrigUntap"]},"image_uris":{"normal":"https://img.scryfall.com/cards/normal/front/3/f/3f290ed2-d1a8-4a90-a3a7-8240652dc109.jpg?1562434953"}}
{"name":"Wickerbough Elder","mana_cost":"{3}{G}","cmc":4.0,"type_line":"Creature - Treefolk Shaman","colors":["G"],"power":"4","toughness":"4","keywords":{"AB$":["Destroy"],"SpellDescription$":["Destroy target artifact or enchantment."],"ValidTgts$":["Artifact","Enchantment"],"TgtPrompt$":["Select target artifact or enchantment"]},"image_uris":{"normal":"https://img.scryfall.com/cards/normal/front/8/3/833dff5c-63b4-413c-9956-67c84d036c2e.jpg?1547517940"}}
{"name":"Wickerbough Elder","mana_cost":"{3}{G}","cmc":4.0,"type_line":"Creature - Treefolk Shaman","colors":["G"],"power":"4","toughness":"4","keywords":{"AB$":["Destroy"],"SpellDescription$":["Destroy target artifact or enchantment."],"ValidTgts$":["Artifact","Enchantment"],"TgtPrompt$":["Select target artifact or enchantment"]},"image_uris":{"normal":"https://img.scryfall.com/cards/normal/front/8/3/833dff5c-63b4-413c-9956-67c84d036c2e.jpg?1547517940"}}
{"name":"Invert the Skies","mana_cost":"{3}{G/U}","cmc":4.0,"type_line":"Instant","colors":["G","U"],"keywords":{"RemoveKeywords$":["Flying"],"SubAbility$":["UPaid"],"SpellDescription$":["Creatures your opponents control lose flying until end of turn if {G} was spent to cast CARDNAME"," and creatures you control gain flying until end of turn if {U} was spent to cast it. (Do both if {G}{U} was spent.)"],"SP$":["AnimateAll"],"ConditionManaSpent$":["G"],"ValidCards$":["Creature.OppCtrl"]},"image_uris":{"normal":"https://img.scryfall.com/cards/normal/front/d/6/d6d0a6f9-478f-43c7-8591-3b601c12ed01.jpg?1568910927"}}
{"name":"Favor of the Overbeing","mana_cost":"{1}{G/U}","cmc":2.0,"type_line":"Enchantment - Aura","colors":["G","U"],"keywords":{"SP$":["Attach"],"ValidTgts$":["Creature"],"AITgts$":["Card.Blue","Card.Green"],"AILogic$":["Pump"]},"image_uris":{"normal":"https://img.scryfall.com/cards/normal/front/9/b/9bf061f8-3aec-429a-bde7-7c110f872416.jpg?1562927911"}}
{"name":"Favor of the Overbeing","mana_cost":"{1}{G/U}","cmc":2.0,"type_line":"Enchantment - Aura","colors":["G","U"],"keywords":{"SP$":["Attach"],"ValidTgts$":["Creature"],"AITgts$":["Card.Blue","Card.Green"],"AILogic$":["Pump"]},"image_uris":{"normal":"https://img.scryfall.com/cards/normal/front/9/b/9bf061f8-3aec-429a-bde7-7c110f872416.jpg?1562927911"}}
{"name":"Wistful Selkie","mana_cost":"{G/U}{G/U}{G/U}","cmc":3.0,"type_line":"Creature - Merfolk Wizard","colors":["G","U"],"power":"2","toughness":"2","keywords":{"Mode$":["ChangesZone"],"ValidCard$":["Card.Self"],"Origin$":["Any"],"TriggerDescription$":["When CARDNAME enters the battlefield"," draw a card."],"Destination$":["Battlefield"],"Execute$":["TrigDraw"]},"image_uris":{"normal":"https://img.scryfall.com/cards/normal/front/f/b/fb74a444-0f77-4369-95db-666be769bfc9.jpg?1562711821"}}
{"name":"Wistful Selkie","mana_cost":"{G/U}{G/U}{G/U}","cmc":3.0,"type_line":"Creature - Merfolk Wizard","colors":["G","U"],"power":"2","toughness":"2","keywords":{"Mode$":["ChangesZone"],"ValidCard$":["Card.Self"],"Origin$":["Any"],"TriggerDescription$":["When CARDNAME enters the battlefield"," draw a card."],"Destination$":["Battlefield"],"Execute$":["TrigDraw"]},"image_uris":{"normal":"https://img.scryfall.com/cards/normal/front/f/b/fb74a444-0f77-4369-95db-666be769bfc9.jpg?1562711821"}}
{"name":"Wistful Selkie","mana_cost":"{G/U}{G/U}{G/U}","cmc":3.0,"type_line":"Creature - Merfolk Wizard","colors":["G","U"],"power":"2","toughness":"2","keywords":{"Mode$":["ChangesZone"],"ValidCard$":["Card.Self"],"Origin$":["Any"],"TriggerDescription$":["When CARDNAME enters the battlefield"," draw a card."],"Destination$":["Battlefield"],"Execute$":["TrigDraw"]},"image_uris":{"normal":"https://img.scryfall.com/cards/normal/front/f/b/fb74a444-0f77-4369-95db-666be769bfc9.jpg?1562711821"}}
{"name":"Shorecrasher Mimic","mana_cost":"{1}{G/U}","cmc":2.0,"type_line":"Creature - Shapeshifter","colors":["G","U"],"power":"2","toughness":"1","keywords":{"Mode$":["SpellCast"],"ValidActivatingPlayer$":["You"],"ValidCard$":["Card.Green+Blue"],"TriggerDescription$":["Whenever you cast a spell thats both green and blue"," CARDNAME has base power and toughness 5/3 until end of turn and gains trample until end of turn."],"TriggerZones$":["Battlefield"],"Execute$":["TrigAnimate"]},"image_uris":{"normal":"https://img.scryfall.com/cards/normal/front/2/4/24babb9e-edc8-484b-9db4-18abbafdf096.jpg?1562902764"}}
{"name":"Shorecrasher Mimic","mana_cost":"{1}{G/U}","cmc":2.0,"type_line":"Creature - Shapeshifter","colors":["G","U"],"power":"2","toughness":"1","keywords":{"Mode$":["SpellCast"],"ValidActivatingPlayer$":["You"],"ValidCard$":["Card.Green+Blue"],"TriggerDescription$":["Whenever you cast a spell thats both green and blue"," CARDNAME has base power and toughness 5/3 until end of turn and gains trample until end of turn."],"TriggerZones$":["Battlefield"],"Execute$":["TrigAnimate"]},"image_uris":{"normal":"https://img.scryfall.com/cards/normal/front/2/4/24babb9e-edc8-484b-9db4-18abbafdf096.jpg?1562902764"}}
{"name":"Shorecrasher Mimic","mana_cost":"{1}{G/U}","cmc":2.0,"type_line":"Creature - Shapeshifter","colors":["G","U"],"power":"2","toughness":"1","keywords":{"Mode$":["SpellCast"],"ValidActivatingPlayer$":["You"],"ValidCard$":["Card.Green+Blue"],"TriggerDescription$":["Whenever you cast a spell thats both green and blue"," CARDNAME has base power and toughness 5/3 until end of turn and gains trample until end of turn."],"TriggerZones$":["Battlefield"],"Execute$":["TrigAnimate"]},"image_uris":{"normal":"https://img.scryfall.com/cards/normal/front/2/4/24babb9e-edc8-484b-9db4-18abbafdf096.jpg?1562902764"}}
{"name":"Fable of Wolf and Owl","mana_cost":"{3}{G/U}{G/U}{G/U}","cmc":6.0,"type_line":"Enchantment","colors":["G","U"],"keywords":{"Mode$":["SpellCast"],"ValidActivatingPlayer$":["You"],"ValidCard$":["Card.Blue"],"OptionalDecider$":["You"],"TriggerDescription$":["Whenever you cast a blue spell"," you may create a 1/1 blue Bird creature token with flying."],"TriggerZones$":["Battlefield"],"Execute$":["TrigBird"]},"image_uris":{"normal":"https://img.scryfall.com/cards/normal/front/b/e/be364b69-aa59-420c-a613-b1d0b303a4e5.jpg?1562935196"}}
{"name":"Dream Fracture","mana_cost":"{1}{U}{U}","cmc":3.0,"type_line":"Instant","colors":["U"],"keywords":{"SubAbility$":["DBDraw"],"SpellDescription$":["Counter target spell. Its controller draws a card. Draw a card."],"SP$":["Counter"],"TargetType$":["Spell"],"ValidTgts$":["Card"],"TgtPrompt$":["Select target spell"]},"image_uris":{"normal":"https://img.scryfall.com/cards/normal/front/1/a/1a5c7858-a57d-449d-8c1f-420d9129c17e.jpg?1562864480"}}
{"name":"Groundling Pouncer","mana_cost":"{1}{G/U}","cmc":2.0,"type_line":"Creature - Faerie","colors":["G","U"],"power":"2","toughness":"1","keywords":{"ActivationLimit$":["1"],"IsPresent$":["Creature.withFlying+OppCtrl"],"AB$":["Pump"],"SpellDescription$":["CARDNAME gets +1/+3 and gains flying until end of turn. Activate this ability only once each turn and only if an opponent controls a creature with flying."],"Defined$":["Self"],"NumAtt$":["1"],"NumDef$":["3"],"KW$":["Flying"]},"image_uris":{"normal":"https://img.scryfall.com/cards/normal/front/5/7/57e7056e-42b9-436a-8302-fcbfa0abd84f.jpg?1562913350"}}
{"name":"Groundling Pouncer","mana_cost":"{1}{G/U}","cmc":2.0,"type_line":"Creature - Faerie","colors":["G","U"],"power":"2","toughness":"1","keywords":{"ActivationLimit$":["1"],"IsPresent$":["Creature.withFlying+OppCtrl"],"AB$":["Pump"],"SpellDescription$":["CARDNAME gets +1/+3 and gains flying until end of turn. Activate this ability only once each turn and only if an opponent controls a creature with flying."],"Defined$":["Self"],"NumAtt$":["1"],"NumDef$":["3"],"KW$":["Flying"]},"image_uris":{"normal":"https://img.scryfall.com/cards/normal/front/5/7/57e7056e-42b9-436a-8302-fcbfa0abd84f.jpg?1562913350"}}
{"name":"Grazing Kelpie","mana_cost":"{3}{G/U}","cmc":4.0,"type_line":"Creature - Beast","colors":["G","U"],"power":"2","toughness":"3","keywords":{"Origin$":["Graveyard"],"AB$":["ChangeZone"],"SpellDescription$":["Put target card from a graveyard on the bottom of its owners library."],"ValidTgts$":["Card"],"Destination$":["Library"],"TgtPrompt$":["Select target card from a graveyard"],"LibraryPosition$":["-1"]},"image_uris":{"normal":"https://img.scryfall.com/cards/normal/front/6/8/68ccef2d-9a1f-4011-89e1-911bcc109b9d.jpg?1562916942"}}
{"name":"Monstrify","mana_cost":"{3}{G}","cmc":4.0,"type_line":"Sorcery","colors":["G"],"keywords":{"SpellDescription$":["Target creature gets +4/+4 until end of turn."],"NumAtt$":["+4"],"SP$":["Pump"],"NumDef$":["+4"],"ValidTgts$":["Creature"],"TgtPrompt$":["Select target creature."]},"image_uris":{"normal":"https://img.scryfall.com/cards/normal/front/5/8/585b52bc-aff5-4406-b55b-1b7decfd80f9.jpg?1562913442"}}
{"name":"Sturdy Hatchling","mana_cost":"{3}{G/U}","cmc":4.0,"type_line":"Creature - Elemental","colors":["G","U"],"power":"6","toughness":"6","keywords":{"Mode$":["SpellCast"],"ValidActivatingPlayer$":["You"],"ValidCard$":["Card.Blue"],"TriggerDescription$":["Whenever you cast a blue spell"," remove a -1/-1 counter from CARDNAME."],"AB$":["Pump"],"SpellDescription$":["CARDNAME gains shroud until end of turn."],"Defined$":["Self"],"TriggerZones$":["Battlefield"],"KW$":["Shroud"],"Execute$":["TrigRemoveCounter"]},"image_uris":{"normal":"https://img.scryfall.com/cards/normal/front/e/4/e41330e2-c6e8-47af-831d-b2d2bd1d06a3.jpg?1562943181"}}
{"name":"Sturdy Hatchling","mana_cost":"{3}{G/U}","cmc":4.0,"type_line":"Creature - Elemental","colors":["G","U"],"power":"6","toughness":"6","keywords":{"Mode$":["SpellCast"],"ValidActivatingPlayer$":["You"],"ValidCard$":["Card.Blue"],"TriggerDescription$":["Whenever you cast a blue spell"," remove a -1/-1 counter from CARDNAME."],"AB$":["Pump"],"SpellDescription$":["CARDNAME gains shroud until end of turn."],"Defined$":["Self"],"TriggerZones$":["Battlefield"],"KW$":["Shroud"],"Execute$":["TrigRemoveCounter"]},"image_uris":{"normal":"https://img.scryfall.com/cards/normal/front/e/4/e41330e2-c6e8-47af-831d-b2d2bd1d06a3.jpg?1562943181"}}
{"name":"Spitting Image","mana_cost":"{4}{G/U}{G/U}","cmc":6.0,"type_line":"Sorcery","colors":["G","U"],"keywords":{"SpellDescription$":["Create a token thats a copy of target creature."],"SP$":["CopyPermanent"],"ValidTgts$":["Creature"],"TgtPrompt$":["Select target creature"]},"image_uris":{"normal":"https://img.scryfall.com/cards/normal/front/e/7/e7c61c3c-bee7-4e4d-aa94-4debc62b74a4.jpg?1562276482"}}
{"name":"Snakeform","mana_cost":"{2}{G/U}","cmc":3.0,"type_line":"Instant","colors":["G","U"],"keywords":{"IsCurse$":["True"],"SpellDescription$":["Until end of turn"," target creature loses all abilities and becomes a green Snake with base power and toughness 1/1. Draw a card."],"Colors$":["Green"],"SP$":["Animate"],"RemoveAllAbilities$":["True"],"Power$":["1"],"ValidTgts$":["Creature"],"TgtPrompt$":["Select target creature"],"RemoveCreatureTypes$":["True"],"SubAbility$":["DBDraw"],"Toughness$":["1"],"OverwriteColors$":["True"],"Types$":["Snake"]},"image_uris":{"normal":"https://img.scryfall.com/cards/normal/front/4/e/4e5a1330-b227-4480-aae7-c8cf350c4898.jpg?1562704081"}}
{"name":"Snakeform","mana_cost":"{2}{G/U}","cmc":3.0,"type_line":"Instant","colors":["G","U"],"keywords":{"IsCurse$":["True"],"SpellDescription$":["Until end of turn"," target creature loses all abilities and becomes a green Snake with base power and toughness 1/1. Draw a card."],"Colors$":["Green"],"SP$":["Animate"],"RemoveAllAbilities$":["True"],"Power$":["1"],"ValidTgts$":["Creature"],"TgtPrompt$":["Select target creature"],"RemoveCreatureTypes$":["True"],"SubAbility$":["DBDraw"],"Toughness$":["1"],"OverwriteColors$":["True"],"Types$":["Snake"]},"image_uris":{"normal":"https://img.scryfall.com/cards/normal/front/4/e/4e5a1330-b227-4480-aae7-c8cf350c4898.jpg?1562704081"}}
{"name":"Snakeform","mana_cost":"{2}{G/U}","cmc":3.0,"type_line":"Instant","colors":["G","U"],"keywords":{"IsCurse$":["True"],"SpellDescription$":["Until end of turn"," target creature loses all abilities and becomes a green Snake with base power and toughness 1/1. Draw a card."],"Colors$":["Green"],"SP$":["Animate"],"RemoveAllAbilities$":["True"],"Power$":["1"],"ValidTgts$":["Creature"],"TgtPrompt$":["Select target creature"],"RemoveCreatureTypes$":["True"],"SubAbility$":["DBDraw"],"Toughness$":["1"],"OverwriteColors$":["True"],"Types$":["Snake"]},"image_uris":{"normal":"https://img.scryfall.com/cards/normal/front/4/e/4e5a1330-b227-4480-aae7-c8cf350c4898.jpg?1562704081"}}
{"name":"Island","mana_cost":"","cmc":0.0,"type_line":"Basic Land - Island","colors":[],"keywords":{},"image_uris":{"normal":"https://img.scryfall.com/cards/normal/front/9/2/92daaa39-cd2f-4c03-8f41-92d99d0a3366.jpg?1581481496"}}
{"name":"Island","mana_cost":"","cmc":0.0,"type_line":"Basic Land - Island","colors":[],"keywords":{},"image_uris":{"normal":"https://img.scryfall.com/cards/normal/front/9/2/92daaa39-cd2f-4c03-8f41-92d99d0a3366.jpg?1581481496"}}
{"name":"Island","mana_cost":"","cmc":0.0,"type_line":"Basic Land - Island","colors":[],"keywords":{},"image_uris":{"normal":"https://img.scryfall.com/cards/normal/front/9/2/92daaa39-cd2f-4c03-8f41-92d99d0a3366.jpg?1581481496"}}
{"name":"Island","mana_cost":"","cmc":0.0,"type_line":"Basic Land - Island","colors":[],"keywords":{},"image_uris":{"normal":"https://img.scryfall.com/cards/normal/front/9/2/92daaa39-cd2f-4c03-8f41-92d99d0a3366.jpg?1581481496"}}
{"name":"Island","mana_cost":"","cmc":0.0,"type_line":"Basic Land - Island","colors":[],"keywords":{},"image_uris":{"normal":"https://img.scryfall.com/cards/normal/front/9/2/92daaa39-cd2f-4c03-8f41-92d99d0a3366.jpg?1581481496"}}
{"name":"Island","mana_cost":"","cmc":0.0,"type_line":"Basic Land - Island","colors":[],"keywords":{},"image_uris":{"normal":"https://img.scryfall.com/cards/normal/front/9/2/92daaa39-cd2f-4c03-8f41-92d99d0a3366.jpg?1581481496"}}
{"name":"Island","mana_cost":"","cmc":0.0,"type_line":"Basic Land - Island","colors":[],"keywords":{},"image_uris":{"normal":"https://img.scryfall.com/cards/normal/front/9/2/92daaa39-cd2f-4c03-8f41-92d99d0a3366.jpg?1581481496"}}
{"name":"Island","mana_cost":"","cmc":0.0,"type_line":"Basic Land - Island","colors":[],"keywords":{},"image_uris":{"normal":"https://img.scryfall.com/cards/normal/front/9/2/92daaa39-cd2f-4c03-8f41-92d99d0a3366.jpg?1581481496"}}
{"name":"Island","mana_cost":"","cmc":0.0,"type_line":"Basic Land - Island","colors":[],"keywords":{},"image_uris":{"normal":"https://img.scryfall.com/cards/normal/front/9/2/92daaa39-cd2f-4c03-8f41-92d99d0a3366.jpg?1581481496"}}
{"name":"Island","mana_cost":"","cmc":0.0,"type_line":"Basic Land - Island","colors":[],"keywords":{},"image_uris":{"normal":"https://img.scryfall.com/cards/normal/front/9/2/92daaa39-cd2f-4c03-8f41-92d99d0a3366.jpg?1581481496"}}
{"name":"Island","mana_cost":"","cmc":0.0,"type_line":"Basic Land - Island","colors":[],"keywords":{},"image_uris":{"normal":"https://img.scryfall.com/cards/normal/front/9/2/92daaa39-cd2f-4c03-8f41-92d99d0a3366.jpg?1581481496"}}
{"name":"Island","mana_cost":"","cmc":0.0,"type_line":"Basic Land - Island","colors":[],"keywords":{},"image_uris":{"normal":"https://img.scryfall.com/cards/normal/front/9/2/92daaa39-cd2f-4c03-8f41-92d99d0a3366.jpg?1581481496"}}
{"name":"Forest","mana_cost":"","cmc":0.0,"type_line":"Basic Land - Forest","colors":[],"keywords":{},"image_uris":{"normal":"https://img.scryfall.com/cards/normal/front/c/4/c4be31c4-9cb3-4a07-865b-5621127df660.jpg?1581482262"}}
{"name":"Forest","mana_cost":"","cmc":0.0,"type_line":"Basic Land - Forest","colors":[],"keywords":{},"image_uris":{"normal":"https://img.scryfall.com/cards/normal/front/c/4/c4be31c4-9cb3-4a07-865b-5621127df660.jpg?1581482262"}}
{"name":"Forest","mana_cost":"","cmc":0.0,"type_line":"Basic Land - Forest","colors":[],"keywords":{},"image_uris":{"normal":"https://img.scryfall.com/cards/normal/front/c/4/c4be31c4-9cb3-4a07-865b-5621127df660.jpg?1581482262"}}
{"name":"Forest","mana_cost":"","cmc":0.0,"type_line":"Basic Land - Forest","colors":[],"keywords":{},"image_uris":{"normal":"https://img.scryfall.com/cards/normal/front/c/4/c4be31c4-9cb3-4a07-865b-5621127df660.jpg?1581482262"}}
{"name":"Forest","mana_cost":"","cmc":0.0,"type_line":"Basic Land - Forest","colors":[],"keywords":{},"image_uris":{"normal":"https://img.scryfall.com/cards/normal/front/c/4/c4be31c4-9cb3-4a07-865b-5621127df660.jpg?1581482262"}}
{"name":"Forest","mana_cost":"","cmc":0.0,"type_line":"Basic Land - Forest","colors":[],"keywords":{},"image_uris":{"normal":"https://img.scryfall.com/cards/normal/front/c/4/c4be31c4-9cb3-4a07-865b-5621127df660.jpg?1581482262"}}
{"name":"Forest","mana_cost":"","cmc":0.0,"type_line":"Basic Land - Forest","colors":[],"keywords":{},"image_uris":{"normal":"https://img.scryfall.com/cards/normal/front/c/4/c4be31c4-9cb3-4a07-865b-5621127df660.jpg?1581482262"}}
{"name":"Forest","mana_cost":"","cmc":0.0,"type_line":"Basic Land - Forest","colors":[],"keywords":{},"image_uris":{"normal":"https://img.scryfall.com/cards/normal/front/c/4/c4be31c4-9cb3-4a07-865b-5621127df660.jpg?1581482262"}}
{"name":"Forest","mana_cost":"","cmc":0.0,"type_line":"Basic Land - Forest","colors":[],"keywords":{},"image_uris":{"normal":"https://img.scryfall.com/cards/normal/front/c/4/c4be31c4-9cb3-4a07-865b-5621127df660.jpg?1581482262"}}
{"name":"Forest","mana_cost":"","cmc":0.0,"type_line":"Basic Land - Forest","colors":[],"keywords":{},"image_uris":{"normal":"https://img.scryfall.com/cards/normal/front/c/4/c4be31c4-9cb3-4a07-865b-5621127df660.jpg?1581482262"}}
{"name":"Forest","mana_cost":"","cmc":0.0,"type_line":"Basic Land - Forest","colors":[],"keywords":{},"image_uris":{"normal":"https://img.scryfall.com/cards/normal/front/c/4/c4be31c4-9cb3-4a07-865b-5621127df660.jpg?1581482262"}}
{"name":"Forest","mana_cost":"","cmc":0.0,"type_line":"Basic Land - Forest","colors":[],"keywords":{},"image_uris":{"normal":"https://img.scryfall.com/cards/normal/front/c/4/c4be31c4-9cb3-4a07-865b-5621127df660.jpg?1581482262"}}
{"name":"Cerulean Wisps","mana_cost":"{U}","cmc":1.0,"type_line":"Instant","colors":["U"],"keywords":{"SubAbility$":["DBUntap"],"SpellDescription$":["Target creature becomes blue until end of turn. Untap that creature. Draw a card."],"Colors$":["Blue"],"SP$":["Animate"],"ValidTgts$":["Creature"],"TgtPrompt$":["Select target creature"],"OverwriteColors$":["True"]},"image_uris":{"normal":"https://img.scryfall.com/cards/normal/front/0/d/0dca4f46-0aad-484f-b4ea-ed61a4fc1a89.jpg?1562826712"}}
{"name":"Viridescent Wisps","mana_cost":"{G}","cmc":1.0,"type_line":"Instant","colors":["G"],"keywords":{"SubAbility$":["DBDraw"],"SpellDescription$":["Target creature becomes green and gets +1/+0 until end of turn. Draw a card."],"NumAtt$":["+1"],"SP$":["Pump"],"NumDef$":["+0"],"ValidTgts$":["Creature"],"TgtPrompt$":["Select target creature"]},"image_uris":{"normal":"https://img.scryfall.com/cards/normal/front/6/c/6c33871f-0e6a-4616-b484-e79b1945255f.jpg?1562831309"}}
{"name":"Selkie Hedge-Mage","mana_cost":"{2}{G/U}","cmc":3.0,"type_line":"Creature - Merfolk Wizard","colors":["G","U"],"power":"2","toughness":"2","keywords":{},"image_uris":{"normal":"https://img.scryfall.com/cards/normal/front/5/f/5f66b0b4-44fc-444d-9181-0b717c9642fa.jpg?1562914934"}}
{"name":"Selkie Hedge-Mage","mana_cost":"{2}{G/U}","cmc":3.0,"type_line":"Creature - Merfolk Wizard","colors":["G","U"],"power":"2","toughness":"2","keywords":{},"image_uris":{"normal":"https://img.scryfall.com/cards/normal/front/5/f/5f66b0b4-44fc-444d-9181-0b717c9642fa.jpg?1562914934"}}
{"name":"Selkie Hedge-Mage","mana_cost":"{2}{G/U}","cmc":3.0,"type_line":"Creature - Merfolk Wizard","colors":["G","U"],"power":"2","toughness":"2","keywords":{},"image_uris":{"normal":"https://img.scryfall.com/cards/normal/front/5/f/5f66b0b4-44fc-444d-9181-0b717c9642fa.jpg?1562914934"}}
