{"name":"Ancient Silverback","mana_cost":"{4}{G}{G}","cmc":6.0,"type_line":"Creature - Ape","colors":["G"],"power":"6","toughness":"5","keywords":{"AB$":["Regenerate"],"SpellDescription$":["Regenerate CARDNAME."]},"image_uris":{"normal":"https://img.scryfall.com/cards/normal/front/7/b/7b24ea58-0690-45d7-a84b-265b6277b59a.jpg?1562789630"}}
{"name":"Blanchwood Armor","mana_cost":"{2}{G}","cmc":3.0,"type_line":"Enchantment - Aura","colors":["G"],"keywords":{"SP$":["Attach"],"ValidTgts$":["Creature"],"AILogic$":["Pump"]},"image_uris":{"normal":"https://img.scryfall.com/cards/normal/front/1/b/1b01d243-9f68-47c7-980b-1418e5f2f3e9.jpg?1562300742"}}
{"name":"Creeping Mold","mana_cost":"{2}{G}{G}","cmc":4.0,"type_line":"Sorcery","colors":["G"],"keywords":{"SpellDescription$":["Destroy target artifact"," enchantment or land."],"SP$":["Destroy"],"ValidTgts$":["Artifact","Enchantment","Land"],"TgtPrompt$":["Select target artifact"," enchantment or land"]},"image_uris":{"normal":"https://img.scryfall.com/cards/normal/front/2/7/277b549c-8691-42b2-9867-802b158a506c.jpg?1576382428"}}
{"name":"Creeping Mold","mana_cost":"{2}{G}{G}","cmc":4.0,"type_line":"Sorcery","colors":["G"],"keywords":{"SpellDescription$":["Destroy target artifact"," enchantment or land."],"SP$":["Destroy"],"ValidTgts$":["Artifact","Enchantment","Land"],"TgtPrompt$":["Select target artifact"," enchantment or land"]},"image_uris":{"normal":"https://img.scryfall.com/cards/normal/front/2/7/277b549c-8691-42b2-9867-802b158a506c.jpg?1576382428"}}
{"name":"Forest","mana_cost":"","cmc":0.0,"type_line":"Basic Land - Forest","colors":[],"keywords":{},"image_uris":{"normal":"https://img.scryfall.com/cards/normal/front/c/4/c4be31c4-9cb3-4a07-865b-5621127df660.jpg?1581482262"}}
{"name":"Forest","mana_cost":"","cmc":0.0,"type_line":"Basic Land - Forest","colors":[],"keywords":{},"image_uris":{"normal":"https://img.scryfall.com/cards/normal/front/c/4/c4be31c4-9cb3-4a07-865b-5621127df660.jpg?1581482262"}}
{"name":"Forest","mana_cost":"","cmc":0.0,"type_line":"Basic Land - Forest","colors":[],"keywords":{},"image_uris":{"normal":"https://img.scryfall.com/cards/normal/front/c/4/c4be31c4-9cb3-4a07-865b-5621127df660.jpg?1581482262"}}
{"name":"Forest","mana_cost":"","cmc":0.0,"type_line":"Basic Land - Forest","colors":[],"keywords":{},"image_uris":{"normal":"https://img.scryfall.com/cards/normal/front/c/4/c4be31c4-9cb3-4a07-865b-5621127df660.jpg?1581482262"}}
{"name":"Forest","mana_cost":"","cmc":0.0,"type_line":"Basic Land - Forest","colors":[],"keywords":{},"image_uris":{"normal":"https://img.scryfall.com/cards/normal/front/c/4/c4be31c4-9cb3-4a07-865b-5621127df660.jpg?1581482262"}}
{"name":"Forest","mana_cost":"","cmc":0.0,"type_line":"Basic Land - Forest","colors":[],"keywords":{},"image_uris":{"normal":"https://img.scryfall.com/cards/normal/front/c/4/c4be31c4-9cb3-4a07-865b-5621127df660.jpg?1581482262"}}
{"name":"Forest","mana_cost":"","cmc":0.0,"type_line":"Basic Land - Forest","colors":[],"keywords":{},"image_uris":{"normal":"https://img.scryfall.com/cards/normal/front/c/4/c4be31c4-9cb3-4a07-865b-5621127df660.jpg?1581482262"}}
{"name":"Forest","mana_cost":"","cmc":0.0,"type_line":"Basic Land - Forest","colors":[],"keywords":{},"image_uris":{"normal":"https://img.scryfall.com/cards/normal/front/c/4/c4be31c4-9cb3-4a07-865b-5621127df660.jpg?1581482262"}}
{"name":"Forest","mana_cost":"","cmc":0.0,"type_line":"Basic Land - Forest","colors":[],"keywords":{},"image_uris":{"normal":"https://img.scryfall.com/cards/normal/front/c/4/c4be31c4-9cb3-4a07-865b-5621127df660.jpg?1581482262"}}
{"name":"Forest","mana_cost":"","cmc":0.0,"type_line":"Basic Land - Forest","colors":[],"keywords":{},"image_uris":{"normal":"https://img.scryfall.com/cards/normal/front/c/4/c4be31c4-9cb3-4a07-865b-5621127df660.jpg?1581482262"}}
{"name":"Forest","mana_cost":"","cmc":0.0,"type_line":"Basic Land - Forest","colors":[],"keywords":{},"image_uris":{"normal":"https://img.scryfall.com/cards/normal/front/c/4/c4be31c4-9cb3-4a07-865b-5621127df660.jpg?1581482262"}}
{"name":"Forest","mana_cost":"","cmc":0.0,"type_line":"Basic Land - Forest","colors":[],"keywords":{},"image_uris":{"normal":"https://img.scryfall.com/cards/normal/front/c/4/c4be31c4-9cb3-4a07-865b-5621127df660.jpg?1581482262"}}
{"name":"Forest","mana_cost":"","cmc":0.0,"type_line":"Basic Land - Forest","colors":[],"keywords":{},"image_uris":{"normal":"https://img.scryfall.com/cards/normal/front/c/4/c4be31c4-9cb3-4a07-865b-5621127df660.jpg?1581482262"}}
{"name":"Forest","mana_cost":"","cmc":0.0,"type_line":"Basic Land - Forest","colors":[],"keywords":{},"image_uris":{"normal":"https://img.scryfall.com/cards/normal/front/c/4/c4be31c4-9cb3-4a07-865b-5621127df660.jpg?1581482262"}}
{"name":"Fyndhorn Elder","mana_cost":"{2}{G}","cmc":3.0,"type_line":"Creature - Elf Druid","colors":["G"],"power":"1","toughness":"1","keywords":{"Produced$":["G"],"AB$":["Mana"],"SpellDescription$":["Add {G}{G}."],"Amount$":["2"]},"image_uris":{"normal":"https://img.scryfall.com/cards/normal/front/8/1/81c125cd-ea49-4511-a78c-42c1f7ce802d.jpg?1562921174"}}
{"name":"Giant Growth","mana_cost":"{G}","cmc":1.0,"type_line":"Instant","colors":["G"],"keywords":{"SpellDescription$":["Target creature gets +3/+3 until end of turn."],"NumAtt$":["+3"],"SP$":["Pump"],"NumDef$":["+3"],"ValidTgts$":["Creature"],"TgtPrompt$":["Select target creature"]},"image_uris":{"normal":"https://img.scryfall.com/cards/normal/front/0/6/06ec9e8b-4bd8-4caf-a559-6514b7ab4ca4.jpg?1557576917"}}
{"name":"Giant Spider","mana_cost":"{3}{G}","cmc":4.0,"type_line":"Creature - Spider","colors":["G"],"power":"2","toughness":"4","keywords":{},"image_uris":{"normal":"https://img.scryfall.com/cards/normal/front/8/0/80996b0d-cd44-445e-96de-677e0018255c.jpg?1562302899"}}
{"name":"Giant Spider","mana_cost":"{3}{G}","cmc":4.0,"type_line":"Creature - Spider","colors":["G"],"power":"2","toughness":"4","keywords":{},"image_uris":{"normal":"https://img.scryfall.com/cards/normal/front/8/0/80996b0d-cd44-445e-96de-677e0018255c.jpg?1562302899"}}
{"name":"Gorilla Chieftain","mana_cost":"{2}{G}{G}","cmc":4.0,"type_line":"Creature - Ape","colors":["G"],"power":"3","toughness":"3","keywords":{"AB$":["Regenerate"],"SpellDescription$":["Regenerate CARDNAME."]},"image_uris":{"normal":"https://img.scryfall.com/cards/normal/front/9/e/9e76185a-519f-4bec-b399-989ebddbab71.jpg?1562244140"}}
{"name":"Grizzly Bears","mana_cost":"{1}{G}","cmc":2.0,"type_line":"Creature - Bear","colors":["G"],"power":"2","toughness":"2","keywords":{},"image_uris":{"normal":"https://img.scryfall.com/cards/normal/front/4/0/409f9b88-f03e-40b6-9883-68c14c37c0de.jpg?1562546736"}}
{"name":"Grizzly Bears","mana_cost":"{1}{G}","cmc":2.0,"type_line":"Creature - Bear","colors":["G"],"power":"2","toughness":"2","keywords":{},"image_uris":{"normal":"https://img.scryfall.com/cards/normal/front/4/0/409f9b88-f03e-40b6-9883-68c14c37c0de.jpg?1562546736"}}
{"name":"Grizzly Bears","mana_cost":"{1}{G}","cmc":2.0,"type_line":"Creature - Bear","colors":["G"],"power":"2","toughness":"2","keywords":{},"image_uris":{"normal":"https://img.scryfall.com/cards/normal/front/4/0/409f9b88-f03e-40b6-9883-68c14c37c0de.jpg?1562546736"}}
{"name":"Llanowar Elves","mana_cost":"{G}","cmc":1.0,"type_line":"Creature - Elf Druid","colors":["G"],"power":"1","toughness":"1","keywords":{"Produced$":["G"],"AB$":["Mana"],"SpellDescription$":["Add {G}."]},"image_uris":{"normal":"https://img.scryfall.com/cards/normal/front/7/3/73542493-cd0b-4bb7-a5b8-8f889c76e4d6.jpg?1562302708"}}
{"name":"Llanowar Elves","mana_cost":"{G}","cmc":1.0,"type_line":"Creature - Elf Druid","colors":["G"],"power":"1","toughness":"1","keywords":{"Produced$":["G"],"AB$":["Mana"],"SpellDescription$":["Add {G}."]},"image_uris":{"normal":"https://img.scryfall.com/cards/normal/front/7/3/73542493-cd0b-4bb7-a5b8-8f889c76e4d6.jpg?1562302708"}}
{"name":"Lure","mana_cost":"{1}{G}{G}","cmc":3.0,"type_line":"Enchantment - Aura","colors":["G"],"keywords":{"Phase$":["Upkeep"],"ValidPlayer$":["You"],"TriggerDescription$":["At the beginning of your upkeep"," you may put a treasure counter on CARDNAME."],"AB$":["GainControl"],"SpellDescription$":["Gain control of target creature with power less than or equal to the number of treasure counters on CARDNAME. (This effect lasts indefinitely.)"],"SP$":["Attach"],"TriggerZones$":["Battlefield"],"ValidTgts$":["Creature"],"TgtPrompt$":["Select target creature with power less than or equal to the number of treasure counters"],"References$":["X"],"Execute$":["TrigPutCounter"],"Mode$":["Phase"],"OptionalDecider$":["You"],"AILogic$":["Pump"]},"image_uris":{"normal":"https://img.scryfall.com/cards/normal/front/7/2/72c8336d-54cf-45af-a9ef-a1428facf91b.jpg?1562850140"}}
{"name":"Pride of Lions","mana_cost":"{3}{G}{G}","cmc":5.0,"type_line":"Creature - Cat","colors":["G"],"power":"4","toughness":"4","keywords":{},"image_uris":{"normal":"https://img.scryfall.com/cards/normal/front/b/5/b521602b-d44b-4c7a-8b28-de0a7cda434b.jpg?1562937684"}}
{"name":"Redwood Treefolk","mana_cost":"{4}{G}","cmc":5.0,"type_line":"Creature - Treefolk","colors":["G"],"power":"3","toughness":"6","keywords":{},"image_uris":{"normal":"https://img.scryfall.com/cards/normal/front/9/c/9cc6d29d-2915-418d-856f-13b05430dfda.jpg?1562244096"}}
{"name":"Regeneration","mana_cost":"{1}{G}","cmc":2.0,"type_line":"Enchantment - Aura","colors":["G"],"keywords":{"AB$":["Regenerate"],"SpellDescription$":["Regenerate enchanted creature."],"Defined$":["Enchanted"],"SP$":["Attach"],"ValidTgts$":["Creature"],"AILogic$":["Pump"]},"image_uris":{"normal":"https://img.scryfall.com/cards/normal/front/4/b/4b848c69-0f64-4631-84b9-6597c359f3ba.jpg?1562547290"}}
{"name":"Rod of Ruin","mana_cost":"{4}","cmc":4.0,"type_line":"Artifact","colors":[],"keywords":{"NumDmg$":["1"],"AB$":["DealDamage"],"SpellDescription$":["CARDNAME deals 1 damage to any target."],"ValidTgts$":["Creature","Player","Planeswalker"],"TgtPrompt$":["Select any target"]},"image_uris":{"normal":"https://img.scryfall.com/cards/normal/front/9/a/9a0e90b8-bc38-4e1c-92ca-ac562cc57e31.jpg?1562832749"}}
{"name":"Spined Wurm","mana_cost":"{4}{G}","cmc":5.0,"type_line":"Creature - Wurm","colors":["G"],"power":"5","toughness":"4","keywords":{},"image_uris":{"normal":"https://img.scryfall.com/cards/normal/front/0/d/0de97b4e-42c7-47e5-a523-a47eadd068f7.jpg?1562428617"}}
{"name":"Stream of Life","mana_cost":"{X}{G}","cmc":1.0,"type_line":"Sorcery","colors":["G"],"keywords":{"SpellDescription$":["Target player gains X life."],"SP$":["GainLife"],"LifeAmount$":["X"],"ValidTgts$":["Player"],"TgtPrompt$":["Select target player"],"References$":["X"]},"image_uris":{"normal":"https://img.scryfall.com/cards/normal/front/3/4/341aa1b2-e600-4580-b0cd-e1582b75dc81.jpg?1562733506"}}
{"name":"Thorn Elemental","mana_cost":"{5}{G}{G}","cmc":7.0,"type_line":"Creature - Elemental","colors":["G"],"power":"7","toughness":"7","keywords":{},"image_uris":{"normal":"https://img.scryfall.com/cards/normal/front/d/a/da901037-20e6-4445-8e7e-1ccd2e8b13ae.jpg?1562743950"}}
{"name":"Trained Armodon","mana_cost":"{1}{G}{G}","cmc":3.0,"type_line":"Creature - Elephant","colors":["G"],"power":"3","toughness":"3","keywords":{},"image_uris":{"normal":"https://img.scryfall.com/cards/normal/front/b/5/b55e0487-3abb-4f2b-b34c-d6ad49164e73.jpg?1562431272"}}
{"name":"Trained Armodon","mana_cost":"{1}{G}{G}","cmc":3.0,"type_line":"Creature - Elephant","colors":["G"],"power":"3","toughness":"3","keywords":{},"image_uris":{"normal":"https://img.scryfall.com/cards/normal/front/b/5/b55e0487-3abb-4f2b-b34c-d6ad49164e73.jpg?1562431272"}}
{"name":"Wild Growth","mana_cost":"{G}","cmc":1.0,"type_line":"Enchantment - Aura","colors":["G"],"keywords":{"Mode$":["TapsForMana"],"ValidCard$":["Card.AttachedBy"],"Static$":["True"],"TriggerDescription$":["Whenever enchanted land is tapped for mana"," its controller adds an additional {G}."],"SP$":["Attach"],"ValidTgts$":["Land"],"AILogic$":["Pump"],"Execute$":["TrigMana"]},"image_uris":{"normal":"https://img.scryfall.com/cards/normal/front/1/8/18fbebd4-d5b4-429a-bfbd-8a7173924d1c.jpg?1561900614"}}
{"name":"Wood Elves","mana_cost":"{2}{G}","cmc":3.0,"type_line":"Creature - Elf Scout","colors":["G"],"power":"1","toughness":"1","keywords":{"Mode$":["ChangesZone"],"ValidCard$":["Creature.Self"],"Origin$":["Any"],"TriggerDescription$":["When CARDNAME enters the battlefield"," search your library for a Forest card and put that card onto the battlefield. Then shuffle your library."],"Destination$":["Battlefield"],"Execute$":["TrigChange"]},"image_uris":{"normal":"https://img.scryfall.com/cards/normal/front/7/7/77f95da2-cbc4-4430-adb7-75f4c469d98e.jpg?1562634082"}}
